{
  "last_updated": "2025-07-09T06:31:24.268134Z",
  "events": [
    {
      "title": "NSW State Jigsaw Puzzle Competition 2025",
      "date": "Upcoming",
      "location": "Marrickville, NSW",
      "link": "https://www.eventbrite.com.au/e/nsw-state-jigsaw-puzzle-competition-2025-tickets-1296486408749?aff=ebdssbneighborhoodbrowse",
      "image": "https://img.evbuc.com/https%3A%2F%2Fcdn.evbuc.com%2Fimages%2F989227923%2F1109996986133%2F1%2Foriginal.20250321-072613?crop=focalpoint&fit=crop&w=400&auto=format%2Ccompress&q=75&sharp=10&fp-x=0.5&fp-y=0.5&s=6d1cd06c64e3c56675aeb45367453835"
    },
    {
      "title": "HSC Workshop: Texts and Human Experiences - English Advanced and Standard",
      "date": "Upcoming",
      "location": "Marrickville, NSW",
      "link": "https://www.eventbrite.com.au/e/hsc-workshop-texts-and-human-experiences-english-advanced-and-standard-tickets-1261825978469?aff=ebdssbneighborhoodbrowse",
      "image": "https://img.evbuc.com/https%3A%2F%2Fcdn.evbuc.com%2Fimages%2F970648883%2F2579267802031%2F1%2Foriginal.20250227-034318?crop=focalpoint&fit=crop&auto=format%2Ccompress&q=75&sharp=10&fp-x=0.005&fp-y=0.005&s=c921aed6bcb6d2de79ab337ea362f08f"
    },
    {
      "title": "Pastry for All",
      "date": "Upcoming",
      "location": "Kensington, NSW",
      "link": "https://www.eventbrite.com.au/e/pastry-for-all-registration-1406872526599?aff=ebdssbneighborhoodbrowse",
      "image": "https://img.evbuc.com/https%3A%2F%2Fcdn.evbuc.com%2Fimages%2F1054524613%2F243879337343%2F1%2Foriginal.20250617-041350?w=512&auto=format%2Ccompress&q=75&sharp=10&rect=0%2C0%2C2160%2C1080&s=966fd13fd308f9cde7911f062b850f81"
    },
    {
      "title": "Penguin Fantasy Fest Sydney",
      "date": "Upcoming",
      "location": "Sydney, NSW",
      "link": "https://www.eventbrite.com.au/e/penguin-fantasy-fest-sydney-tickets-1383372557559?aff=ebdssbneighborhoodbrowse",
      "image": "https://img.evbuc.com/https%3A%2F%2Fcdn.evbuc.com%2Fimages%2F1040327973%2F1593803741683%2F1%2Foriginal.20250528-042202?w=400&auto=format%2Ccompress&q=75&sharp=10&s=bd28e987c31c312b22e9713a64850252"
    },
    {
      "title": "HOSHI X SMASH! Official Pre Party",
      "date": "Upcoming",
      "location": "Darling Park, NSW",
      "link": "https://www.eventbrite.com.au/e/hoshi-x-smash-official-pre-party-tickets-1363685061729?aff=ebdssbcitybrowsenightlife",
      "image": "https://img.evbuc.com/https%3A%2F%2Fcdn.evbuc.com%2Fimages%2F1029227163%2F2245701384243%2F1%2Foriginal.20250512-235339?crop=focalpoint&fit=crop&w=512&auto=format%2Ccompress&q=75&sharp=10&fp-x=0.5&fp-y=0.5&s=8bb116547952e65d9f49dba708fbd880"
    },
    {
      "title": "The Ultimate Backpacker & International Boat Party + FREE After Party",
      "date": "Upcoming",
      "location": "Circular Quay, NSW",
      "link": "https://www.eventbrite.com.au/e/the-ultimate-backpacker-international-boat-party-free-after-party-tickets-1452932332719?aff=ebdssbcitybrowsenightlife",
      "image": "https://img.evbuc.com/https%3A%2F%2Fcdn.evbuc.com%2Fimages%2F1065027583%2F363582059739%2F1%2Foriginal.20250702-115201?w=512&auto=format%2Ccompress&q=75&sharp=10&rect=0%2C0%2C2160%2C1080&s=79d2111b5e472ceb70ef5b7371c5d302"
    },
    {
      "title": "FRI 11 JUL - WINTER WONDERLAND @ WAO SUPERCLUB",
      "date": "Upcoming",
      "location": "Sydney, NSW",
      "link": "https://www.eventbrite.com.au/e/fri-11-jul-winter-wonderland-wao-superclub-tickets-1404622647149?aff=ebdssbcitybrowsenightlife",
      "image": "https://img.evbuc.com/https%3A%2F%2Fcdn.evbuc.com%2Fimages%2F1054355193%2F713796481473%2F1%2Foriginal.20250616-231619?w=512&auto=format%2Ccompress&q=75&sharp=10&rect=0%2C0%2C2160%2C1080&s=61292fbbeb3c8fa15766e27f4207ad53"
    },
    {
      "title": "LEVELS SYDNEY | 18.07.25 | VORTEK'S (FR) + STAN CHRIST (NL)",
      "date": "Upcoming",
      "location": "Sydney, NSW",
      "link": "https://www.eventbrite.com.au/e/levels-sydney-180725-vorteks-fr-stan-christ-nl-tickets-1383458665109?aff=ebdssbcitybrowsenightlife",
      "image": "https://img.evbuc.com/https%3A%2F%2Fcdn.evbuc.com%2Fimages%2F1040380093%2F193932742550%2F1%2Foriginal.20250528-070027?w=512&auto=format%2Ccompress&q=75&sharp=10&rect=0%2C22%2C1920%2C960&s=050f261c6998c2a9f222505c7a269cb6"
    },
    {
      "title": "Bollywood Club presents DISCOSTAN at Zeta Bar Hilton, Sydney",
      "date": "Upcoming",
      "location": "Sydney, NSW",
      "link": "https://www.eventbrite.com.au/e/bollywood-club-presents-discostan-at-zeta-bar-hilton-sydney-tickets-1418817674859?aff=ebdssbcitybrowse",
      "image": "https://img.evbuc.com/https%3A%2F%2Fcdn.evbuc.com%2Fimages%2F1055627073%2F99150026607%2F1%2Foriginal.20250618-112739?h=230&w=460&auto=format%2Ccompress&q=75&sharp=10&rect=0%2C0%2C2160%2C1080&s=7bc15ec76b88d96b6cb69fc5440326ed"
    },
    {
      "title": "HOSHI X SMASH! Official Pre Party",
      "date": "Upcoming",
      "location": "Darling Park, NSW",
      "link": "https://www.eventbrite.com.au/e/hoshi-x-smash-official-pre-party-tickets-1363685061729?aff=ebdssbcitybrowse",
      "image": "https://img.evbuc.com/https%3A%2F%2Fcdn.evbuc.com%2Fimages%2F1029227163%2F2245701384243%2F1%2Foriginal.20250512-235339?crop=focalpoint&fit=crop&w=512&auto=format%2Ccompress&q=75&sharp=10&fp-x=0.5&fp-y=0.5&s=8bb116547952e65d9f49dba708fbd880"
    },
    {
      "title": "Quantum Future Talent: Open Day & Careers Fair",
      "date": "Upcoming",
      "location": "Sydney, NSW",
      "link": "https://www.eventbrite.com.au/e/quantum-future-talent-open-day-careers-fair-tickets-1326182570769?aff=ebdssbcitybrowse",
      "image": "https://img.evbuc.com/https%3A%2F%2Fcdn.evbuc.com%2Fimages%2F1024044053%2F477764192637%2F1%2Foriginal.20250506-041754?w=512&auto=format%2Ccompress&q=75&sharp=10&rect=0%2C0%2C2160%2C1080&s=45818123c269f7bf7236a6a2ae32c12e"
    },
    {
      "title": "LITTLE NATIONAL x KATIE MARTIN RUN CLUB",
      "date": "Upcoming",
      "location": "Sydney, NSW",
      "link": "https://www.eventbrite.com.au/e/little-national-x-katie-martin-run-club-tickets-1436037088589?aff=ebdssbcitybrowse",
      "image": "https://img.evbuc.com/https%3A%2F%2Fcdn.evbuc.com%2Fimages%2F1060939483%2F223553011126%2F1%2Foriginal.20250626-063208?w=512&auto=format%2Ccompress&q=75&sharp=10&rect=0%2C0%2C2160%2C1080&s=f4ff84fdb7777cb76fa8b1499e8412c8"
    },
    {
      "title": "LEVELS SYDNEY | 18.07.25 | VORTEK'S (FR) + STAN CHRIST (NL)",
      "date": "Upcoming",
      "location": "Sydney, NSW",
      "link": "https://www.eventbrite.com.au/e/levels-sydney-180725-vorteks-fr-stan-christ-nl-tickets-1383458665109?aff=ebdssbcitybrowse",
      "image": "https://img.evbuc.com/https%3A%2F%2Fcdn.evbuc.com%2Fimages%2F1040380093%2F193932742550%2F1%2Foriginal.20250528-070027?w=512&auto=format%2Ccompress&q=75&sharp=10&rect=0%2C22%2C1920%2C960&s=050f261c6998c2a9f222505c7a269cb6"
    },
    {
      "title": "Venture & Capital - Investment Conference - SYDNEY 2025",
      "date": "Upcoming",
      "location": "Sydney, NSW",
      "link": "https://www.eventbrite.com.au/e/venture-capital-investment-conference-sydney-2025-tickets-1280280536549?aff=ebdssbcitybrowse",
      "image": "https://img.evbuc.com/https%3A%2F%2Fcdn.evbuc.com%2Fimages%2F1040193773%2F54901145563%2F1%2Foriginal.20250527-233442?w=512&auto=format%2Ccompress&q=75&sharp=10&rect=0%2C0%2C2160%2C1080&s=29a0cc624cd674497a74bb8b915ab17b"
    },
    {
      "title": "CRAVE feat. PAUL VAN DYK",
      "date": "Upcoming",
      "location": "Sydney, NSW",
      "link": "https://www.eventbrite.com.au/e/crave-feat-paul-van-dyk-tickets-1425038952869?aff=ebdssbcitybrowse",
      "image": "https://img.evbuc.com/https%3A%2F%2Fcdn.evbuc.com%2Fimages%2F1057654233%2F566220113875%2F1%2Foriginal.20250621-011217?w=512&auto=format%2Ccompress&q=75&sharp=10&rect=0%2C73%2C1920%2C960&s=198f6ab0525410ee452612e6c3c148f8"
    },
    {
      "title": "Sydney Tattoo Convention 2025 \u2013 Australia's Premier Tattoo Expo",
      "date": "Upcoming",
      "location": "Sydney, NSW",
      "link": "https://www.eventbrite.com.au/e/sydney-tattoo-convention-2025-australias-premier-tattoo-expo-tickets-1036514722437?aff=ebdssbcitybrowse",
      "image": "https://img.evbuc.com/https%3A%2F%2Fcdn.evbuc.com%2Fimages%2F951047303%2F203978083134%2F1%2Foriginal.20250203-055351?w=512&auto=format%2Ccompress&q=75&sharp=10&rect=0%2C0%2C9000%2C4500&s=d29d56466f8e0c7ed231ea575b30f748"
    },
    {
      "title": "How to Get SBA Financing to Buy Your First Business",
      "date": "Upcoming",
      "location": "online",
      "link": "https://www.eventbrite.com/e/how-to-get-sba-financing-to-buy-your-first-business-tickets-1381112377299?aff=ebdssbcitybrowse",
      "image": "https://img.evbuc.com/https%3A%2F%2Fcdn.evbuc.com%2Fimages%2F1066401463%2F312980622916%2F1%2Foriginal.20250703-232141?w=400&auto=format%2Ccompress&q=75&sharp=10&s=47773875fec2c5c4e5f49e05b3d8ba88"
    },
    {
      "title": "JOAN MIRO: DRAWING IS POETRY",
      "date": "Upcoming",
      "location": "online",
      "link": "https://www.eventbrite.co.uk/e/joan-miro-drawing-is-poetry-tickets-1462293000729?aff=ebdssbcitybrowse",
      "image": "https://img.evbuc.com/https%3A%2F%2Fcdn.evbuc.com%2Fimages%2F774066959%2F185750211993%2F1%2Foriginal.20240522-180055?w=512&auto=format%2Ccompress&q=75&sharp=10&rect=0%2C0%2C2048%2C1024&s=68672b14f5d13b3a4f401ba8ad086653"
    },
    {
      "title": "From Chalkboards to Chatbots: The Evolution of Teaching with AI",
      "date": "Upcoming",
      "location": "online",
      "link": "https://www.eventbrite.com.au/e/from-chalkboards-to-chatbots-the-evolution-of-teaching-with-ai-tickets-1393613317949?aff=ebdssbcitybrowse",
      "image": "https://img.evbuc.com/https%3A%2F%2Fcdn.evbuc.com%2Fimages%2F1056972603%2F1401304503913%2F1%2Foriginal.20250619-235656?w=512&auto=format%2Ccompress&q=75&sharp=10&rect=0%2C0%2C2160%2C1080&s=6155129b12ac435d27a29b79b44d4861"
    },
    {
      "title": "PMI Melbourne Chapter Lunch & Learn - July 2025",
      "date": "Upcoming",
      "location": "online",
      "link": "https://www.eventbrite.com.au/e/pmi-melbourne-chapter-lunch-learn-july-2025-tickets-1343386327669?aff=ebdssbcitybrowse",
      "image": "https://img.evbuc.com/https%3A%2F%2Fcdn.evbuc.com%2Fimages%2F1018757723%2F196539100230%2F1%2Foriginal.20250429-015210?w=512&auto=format%2Ccompress&q=75&sharp=10&rect=0%2C100%2C3002%2C1501&s=7f0cb3b249215c405272fa97eaccdc83"
    },
    {
      "title": "Career Fair: Exclusive Tech Hiring Event-New Tickets Available",
      "date": "Upcoming",
      "location": "online",
      "link": "https://www.eventbrite.com/e/career-fair-exclusive-tech-hiring-event-new-tickets-available-tickets-63049080497?aff=ebdssbcitybrowse",
      "image": "https://img.evbuc.com/https%3A%2F%2Fcdn.evbuc.com%2Fimages%2F682597209%2F197361445633%2F1%2Foriginal.20240125-160053?w=512&auto=format%2Ccompress&q=75&sharp=10&rect=0%2C0%2C940%2C470&s=1790a7734766e877ae40e832f440984d"
    },
    {
      "title": "We\u2019re Building What\u2019s Next: 10+ Startups at Greenbook\u2019s Tech Showcase",
      "date": "Upcoming",
      "location": "online",
      "link": "https://www.eventbrite.com/e/were-building-whats-next-10-startups-at-greenbooks-tech-showcase-tickets-1393096191209?aff=ebdssbcitybrowse",
      "image": "https://img.evbuc.com/https%3A%2F%2Fcdn.evbuc.com%2Fimages%2F1043890573%2F2578780454311%2F1%2Foriginal.20250602-151602?crop=focalpoint&fit=crop&w=512&auto=format%2Ccompress&q=75&sharp=10&fp-x=0.5&fp-y=0.5&s=46978dc219ac6c7844f018175b85a792"
    },
    {
      "title": "Single  and Intentional (Ages 25+ preferred)** Virtual Event**",
      "date": "Upcoming",
      "location": "online",
      "link": "https://www.eventbrite.com/e/single-and-intentional-ages-25-preferred-virtual-event-tickets-1045297481907?aff=ebdssbcitybrowse",
      "image": "https://img.evbuc.com/https%3A%2F%2Fcdn.evbuc.com%2Fimages%2F708001649%2F1999088473903%2F1%2Foriginal.20240229-050947?w=512&auto=format%2Ccompress&q=75&sharp=10&rect=0%2C1148%2C2912%2C1456&s=583581000d4b553b8354c355bdb7f322"
    },
    {
      "title": "No Cost On-Line Coursera Certification Courses For Military and Spouse",
      "date": "Upcoming",
      "location": "online",
      "link": "https://www.eventbrite.com/e/no-cost-on-line-coursera-certification-courses-for-military-and-spouse-tickets-165655358637?aff=ebdssbcitybrowse",
      "image": "https://img.evbuc.com/https%3A%2F%2Fcdn.evbuc.com%2Fimages%2F631748609%2F122310519079%2F1%2Foriginal.20231031-040429?w=512&auto=format%2Ccompress&q=75&sharp=10&rect=0%2C0%2C2160%2C1080&s=9b7a42e3580929f655116c091d698c90"
    },
    {
      "title": "GOLDEN HOUR: NEON LIGHTS BOAT PARTY",
      "date": "Upcoming",
      "location": "Circular Quay, NSW",
      "link": "https://www.eventbrite.com.au/e/golden-hour-neon-lights-boat-party-tickets-1406753961969?aff=ebdssbcitybrowse",
      "image": "https://img.evbuc.com/https%3A%2F%2Fcdn.evbuc.com%2Fimages%2F1049487653%2F363582059739%2F1%2Foriginal.20250610-020734?w=512&auto=format%2Ccompress&q=75&sharp=10&rect=0%2C2%2C1170%2C585&s=2c67ce1c8ee71b706ba2c6f5de996c3d"
    },
    {
      "title": "Working Across Worlds : Japan-Australia Career Pathways",
      "date": "Upcoming",
      "location": "Barangaroo, NSW",
      "link": "https://www.eventbrite.com/e/working-across-worlds-japan-australia-career-pathways-tickets-1404596348489?aff=ebdssbcitybrowse",
      "image": "https://img.evbuc.com/https%3A%2F%2Fcdn.evbuc.com%2Fimages%2F1060851403%2F2788364927371%2F1%2Foriginal.20250626-020808?w=512&auto=format%2Ccompress&q=75&sharp=10&rect=0%2C0%2C2160%2C1080&s=2465e2858ecbc75b5031dd936210dcf5"
    },
    {
      "title": "Unity Mambo Experience 2025 - Sydney from the 11 to the 13 July",
      "date": "Upcoming",
      "location": "Sydney, NSW",
      "link": "https://www.eventbrite.com.au/e/unity-mambo-experience-2025-sydney-from-the-11-to-the-13-july-tickets-1167021806639?aff=ebdssbcitybrowse",
      "image": "https://img.evbuc.com/https%3A%2F%2Fcdn.evbuc.com%2Fimages%2F1040345743%2F471997391639%2F1%2Foriginal.20250528-051243?w=333&auto=format%2Ccompress&q=75&sharp=10&s=2d338b698683a4b5117a1fb53997c05f"
    },
    {
      "title": "Taller: Establecerse en Australia: Decisiones que marcan el camino",
      "date": "Upcoming",
      "location": "Sydney, NSW",
      "link": "https://www.eventbrite.com.au/e/taller-establecerse-en-australia-decisiones-que-marcan-el-camino-tickets-1445376844049?aff=ebdssbcitybrowse",
      "image": "https://img.evbuc.com/https%3A%2F%2Fcdn.evbuc.com%2Fimages%2F1063041303%2F1421445651893%2F1%2Foriginal.20250630-014316?w=512&auto=format%2Ccompress&q=75&sharp=10&rect=0%2C189%2C1080%2C540&s=d604e6f9e00c890630c4347f30d8e57a"
    },
    {
      "title": "The Ultimate Backpacker & International Boat Party + FREE After Party",
      "date": "Upcoming",
      "location": "Circular Quay, NSW",
      "link": "https://www.eventbrite.com.au/e/the-ultimate-backpacker-international-boat-party-free-after-party-tickets-1452932332719?aff=ebdssbcitybrowse",
      "image": "https://img.evbuc.com/https%3A%2F%2Fcdn.evbuc.com%2Fimages%2F1065027583%2F363582059739%2F1%2Foriginal.20250702-115201?w=512&auto=format%2Ccompress&q=75&sharp=10&rect=0%2C0%2C2160%2C1080&s=79d2111b5e472ceb70ef5b7371c5d302"
    },
    {
      "title": "FRI 11 JUL - WINTER WONDERLAND @ WAO SUPERCLUB",
      "date": "Upcoming",
      "location": "Sydney, NSW",
      "link": "https://www.eventbrite.com.au/e/fri-11-jul-winter-wonderland-wao-superclub-tickets-1404622647149?aff=ebdssbcitybrowse",
      "image": "https://img.evbuc.com/https%3A%2F%2Fcdn.evbuc.com%2Fimages%2F1054355193%2F713796481473%2F1%2Foriginal.20250616-231619?w=512&auto=format%2Ccompress&q=75&sharp=10&rect=0%2C0%2C2160%2C1080&s=61292fbbeb3c8fa15766e27f4207ad53"
    },
    {
      "title": "Breath & Body Reset \u2014 Somatic Breathwork for Stress & Tension",
      "date": "Upcoming",
      "location": "Cronulla, NSW",
      "link": "https://www.eventbrite.com.au/e/breath-body-reset-somatic-breathwork-for-stress-tension-tickets-1426601897679?aff=ebdssbcitybrowse",
      "image": "https://img.evbuc.com/https%3A%2F%2Fcdn.evbuc.com%2Fimages%2F1058515253%2F2006797411353%2F1%2Foriginal.20250623-113046?crop=focalpoint&fit=crop&w=512&auto=format%2Ccompress&q=75&sharp=10&fp-x=0.157854484789&fp-y=0.393313336728&s=9868c4434a32c6b404c6d6217f3bbb14"
    },
    {
      "title": "[SYDNEY] Sunday - 13.07.2025 - ANDREE RIGHT HAND & DJ TILO, MC MINAMI",
      "date": "Upcoming",
      "location": "Sydney, NSW",
      "link": "https://www.eventbrite.com.au/e/sydney-sunday-13072025-andree-right-hand-dj-tilo-mc-minami-tickets-1396216193219?aff=ebdssbcitybrowse",
      "image": "https://img.evbuc.com/https%3A%2F%2Fcdn.evbuc.com%2Fimages%2F1045625013%2F1614174898533%2F1%2Foriginal.20250604-114559?w=512&auto=format%2Ccompress&q=75&sharp=10&rect=0%2C28%2C2400%2C1200&s=7cffd848aea52583678fa9deb6e2a534"
    }
  ]
}