{
  "last_updated": "2026-03-28T18:41:53.550530Z",
  "events": [
    {
      "title": "Create a Memoir Film - Capture your Family History",
      "date": "Upcoming",
      "location": "Haberfield, NSW",
      "link": "https://www.eventbrite.com.au/e/create-a-memoir-film-capture-your-family-history-tickets-1977325370411?aff=ebdssbneighborhoodbrowse",
      "image": "https://img.evbuc.com/https%3A%2F%2Fcdn.evbuc.com%2Fimages%2F1172573490%2F2597958638401%2F1%2Foriginal.20251209-010343?w=512&auto=format%2Ccompress&q=75&sharp=10&rect=0%2C0%2C2160%2C1080&s=11e2e539bf4650f0143d7db9ccb7ff44"
    },
    {
      "title": "Author Talk: Natasha Lester and Cassie Hamer with The Chateau on Sunset",
      "date": "Upcoming",
      "location": "Double Bay, NSW",
      "link": "https://www.eventbrite.com.au/e/author-talk-natasha-lester-and-cassie-hamer-with-the-chateau-on-sunset-tickets-1980757141932?aff=ebdssbneighborhoodbrowse",
      "image": "https://img.evbuc.com/https%3A%2F%2Fcdn.evbuc.com%2Fimages%2F1179560271%2F2849388593661%2F1%2Foriginal.20260311-054107?w=400&auto=format%2Ccompress&q=75&sharp=10&s=bf603ccad9ad2e671555dce9459a2b14"
    },
    {
      "title": "Engineering the Future: AI Evolving",
      "date": "Upcoming",
      "location": "Sydney, NSW",
      "link": "https://www.eventbrite.com.au/e/engineering-the-future-ai-evolving-registration-1983420665603?aff=ebdssbneighborhoodbrowse",
      "image": "https://img.evbuc.com/https%3A%2F%2Fcdn.evbuc.com%2Fimages%2F1177887963%2F243760117606%2F1%2Foriginal.20260218-230952?w=512&auto=format%2Ccompress&q=75&sharp=10&rect=0%2C0%2C2160%2C1080&s=4da3488ea9c3149b7ec3aee6f9a219ec"
    },
    {
      "title": "AI Made Simple 3: How AI Learns",
      "date": "Upcoming",
      "location": "North Sydney, NSW",
      "link": "https://www.eventbrite.com.au/e/ai-made-simple-3-how-ai-learns-tickets-1982860735838?aff=ebdssbneighborhoodbrowse",
      "image": "https://img.evbuc.com/https%3A%2F%2Fcdn.evbuc.com%2Fimages%2F1177439423%2F1334921392293%2F1%2Foriginal.20260213-031541?crop=focalpoint&fit=crop&w=400&auto=format%2Ccompress&q=75&sharp=10&fp-x=0.5&fp-y=0.5&s=c082ccda12a69a626835aea83e90bbb0"
    },
    {
      "title": "Sublime Rewind | 30 Year Anniversary | 2026",
      "date": "Upcoming",
      "location": "Darling Park, NSW",
      "link": "https://www.eventbrite.com.au/e/sublime-rewind-30-year-anniversary-2026-tickets-1982059164316?aff=ebdssbcitybrowsenightlife",
      "image": "https://img.evbuc.com/https%3A%2F%2Fcdn.evbuc.com%2Fimages%2F1177706195%2F245967499872%2F1%2Foriginal.20260217-084003?w=512&auto=format%2Ccompress&q=75&sharp=10&rect=0%2C23%2C2400%2C1200&s=49a926b4973798e65b305dbce5c35d72"
    },
    {
      "title": "Ami Easter Thursday Biggest International Party",
      "date": "Upcoming",
      "location": "Sydney, NSW",
      "link": "https://www.eventbrite.com.au/e/ami-easter-thursday-biggest-international-party-tickets-1984258823556?aff=ebdssbcitybrowsenightlife",
      "image": "https://img.evbuc.com/https%3A%2F%2Fcdn.evbuc.com%2Fimages%2F1178765334%2F2409601006343%2F1%2Foriginal.20260302-055838?w=512&auto=format%2Ccompress&q=75&sharp=10&rect=0%2C137%2C1080%2C540&s=166dbb49d031ae06dd3e1da3a375b753"
    },
    {
      "title": "240KM/H -  Sydney Showcase",
      "date": "Upcoming",
      "location": "Sydney, NSW",
      "link": "https://www.eventbrite.com.au/e/240kmh-sydney-showcase-tickets-1984352175775?aff=ebdssbcitybrowsenightlife",
      "image": "https://img.evbuc.com/https%3A%2F%2Fcdn.evbuc.com%2Fimages%2F1178873204%2F282597088620%2F1%2Foriginal.20260303-044330?w=512&auto=format%2Ccompress&q=75&sharp=10&rect=0%2C0%2C4320%2C2160&s=7026905953d87c920a7f180e00846d3f"
    },
    {
      "title": "Supreme Speed Society presents: SYSTEM OVERDRIVE!",
      "date": "Upcoming",
      "location": "Sydney, NSW",
      "link": "https://www.eventbrite.com/e/supreme-speed-society-presents-system-overdrive-tickets-1983659833962?aff=ebdssbcitybrowsenightlife",
      "image": "https://img.evbuc.com/https%3A%2F%2Fcdn.evbuc.com%2Fimages%2F1178474841%2F2972356374591%2F1%2Foriginal.20260226-015955?w=512&auto=format%2Ccompress&q=75&sharp=10&rect=0%2C0%2C2160%2C1080&s=f18d249103a6daf2774db96b342c9a3a"
    },
    {
      "title": "Capital 2026",
      "date": "Upcoming",
      "location": "Sydney, NSW",
      "link": "https://www.eventbrite.com.au/e/capital-2026-tickets-1983329476855?aff=ebdssbcitybrowse",
      "image": "https://img.evbuc.com/https%3A%2F%2Fcdn.evbuc.com%2Fimages%2F1177695986%2F54901145563%2F1%2Foriginal.20260217-034200?h=230&w=460&auto=format%2Ccompress&q=75&sharp=10&rect=0%2C0%2C2160%2C1080&s=d73b3518bcc370e162e3807f95b2568a"
    },
    {
      "title": "Homemade Saturdays: Free Entry + Complimentary Drink",
      "date": "Upcoming",
      "location": "Sydney, NSW",
      "link": "https://www.eventbrite.com.au/e/homemade-saturdays-free-entry-complimentary-drink-tickets-887309505617?aff=ebdssbcitybrowse",
      "image": "https://img.evbuc.com/https%3A%2F%2Fcdn.evbuc.com%2Fimages%2F748918359%2F2055543935043%2F1%2Foriginal.20240422-010025?w=512&auto=format%2Ccompress&q=75&sharp=10&rect=0%2C0%2C2160%2C1080&s=6de3c49714627a4ec6139403c1c4be75"
    },
    {
      "title": "Lord Mayor\u2019s Welcome for International Students 2026",
      "date": "Upcoming",
      "location": "Sydney, NSW",
      "link": "https://www.eventbrite.com.au/e/lord-mayors-welcome-for-international-students-2026-tickets-1981065165238?aff=ebdssbcitybrowse",
      "image": "https://img.evbuc.com/https%3A%2F%2Fcdn.evbuc.com%2Fimages%2F1175396098%2F2421228637971%2F1%2Foriginal.20260120-230913?w=512&auto=format%2Ccompress&q=75&sharp=10&rect=0%2C443%2C3000%2C1500&s=1e7069e2ff490348f7f5eb57579aa121"
    },
    {
      "title": "Engineering the Future: AI Evolving",
      "date": "Upcoming",
      "location": "Sydney, NSW",
      "link": "https://www.eventbrite.com.au/e/engineering-the-future-ai-evolving-registration-1983420665603?aff=ebdssbcitybrowse",
      "image": "https://img.evbuc.com/https%3A%2F%2Fcdn.evbuc.com%2Fimages%2F1177887963%2F243760117606%2F1%2Foriginal.20260218-230952?w=512&auto=format%2Ccompress&q=75&sharp=10&rect=0%2C0%2C2160%2C1080&s=4da3488ea9c3149b7ec3aee6f9a219ec"
    },
    {
      "title": "em4. Sydney",
      "date": "Upcoming",
      "location": "Sydney, NSW",
      "link": "https://www.eventbrite.com.au/e/em4-sydney-tickets-1984447281238?aff=ebdssbcitybrowse",
      "image": "https://img.evbuc.com/https%3A%2F%2Fcdn.evbuc.com%2Fimages%2F1178983326%2F1797416342223%2F1%2Foriginal.20260304-061021?crop=focalpoint&fit=crop&w=512&auto=format%2Ccompress&q=75&sharp=10&fp-x=0.5&fp-y=0.5&s=9530cd513e77891245a6f54a3378caa6"
    },
    {
      "title": "240KM/H -  Sydney Showcase",
      "date": "Upcoming",
      "location": "Sydney, NSW",
      "link": "https://www.eventbrite.com.au/e/240kmh-sydney-showcase-tickets-1984352175775?aff=ebdssbcitybrowse",
      "image": "https://img.evbuc.com/https%3A%2F%2Fcdn.evbuc.com%2Fimages%2F1178873204%2F282597088620%2F1%2Foriginal.20260303-044330?w=512&auto=format%2Ccompress&q=75&sharp=10&rect=0%2C0%2C4320%2C2160&s=7026905953d87c920a7f180e00846d3f"
    },
    {
      "title": "Long weekend Sunday sesh",
      "date": "Upcoming",
      "location": "Sydney, NSW",
      "link": "https://www.eventbrite.com.au/e/long-weekend-sunday-sesh-tickets-1984705285937?aff=ebdssbcitybrowse",
      "image": "https://img.evbuc.com/https%3A%2F%2Fcdn.evbuc.com%2Fimages%2F1173984518%2F370592850131%2F1%2Foriginal.20260105-074234?w=512&auto=format%2Ccompress&q=75&sharp=10&rect=0%2C0%2C1080%2C540&s=0f2035df96d3c2174fa54e306ebb4dff"
    },
    {
      "title": "80s, 90s & 00s Silent Disco By Moonlight in Sydney Town Hall - Sat 18th Apr",
      "date": "Upcoming",
      "location": "Sydney, NSW",
      "link": "https://www.eventbrite.co.uk/e/80s-90s-00s-silent-disco-by-moonlight-in-sydney-town-hall-sat-18th-apr-tickets-1972772712288?aff=ebdssbcitybrowse",
      "image": "https://img.evbuc.com/https%3A%2F%2Fcdn.evbuc.com%2Fimages%2F807792929%2F61565826027%2F1%2Foriginal.20240715-112105?w=512&auto=format%2Ccompress&q=75&sharp=10&rect=1%2C172%2C3982%2C1991&s=1e7661665fc0d7831a1b181de8716bf0"
    },
    {
      "title": "B&N Midday Mystery Virtually Presents: Tana French's THE KEEPER!",
      "date": "Upcoming",
      "location": "online",
      "link": "https://www.eventbrite.com/e/bn-midday-mystery-virtually-presents-tana-frenchs-the-keeper-tickets-1979236524725?aff=ebdssbcitybrowse",
      "image": "https://img.evbuc.com/https%3A%2F%2Fcdn.evbuc.com%2Fimages%2F1179027317%2F57848390869%2F1%2Foriginal.20260304-172914?crop=focalpoint&fit=crop&w=512&auto=format%2Ccompress&q=75&sharp=10&fp-x=0.139&fp-y=0.487&s=cc51c76a4360049dbc1fe65a5af10b58"
    },
    {
      "title": "NASA's Artemis II Mission Launch",
      "date": "Upcoming",
      "location": "online",
      "link": "https://www.eventbrite.com/e/nasas-artemis-ii-mission-launch-registration-1074571685839?aff=ebdssbcitybrowse",
      "image": "https://img.evbuc.com/https%3A%2F%2Fcdn.evbuc.com%2Fimages%2F1016696783%2F977011528923%2F1%2Foriginal.20250425-135833?crop=focalpoint&fit=crop&w=512&auto=format%2Ccompress&q=75&sharp=10&fp-x=0.492424242424&fp-y=0.598006644518&s=948c860134aff04a589248ad2edef2a5"
    },
    {
      "title": "Seminar on Big Data, Data Science and Machine Learning",
      "date": "Upcoming",
      "location": "online",
      "link": "https://www.eventbrite.com/e/seminar-on-big-data-data-science-and-machine-learning-tickets-787580734177?aff=ebdssbcitybrowse",
      "image": "https://img.evbuc.com/https%3A%2F%2Fcdn.evbuc.com%2Fimages%2F144527461%2F198476887449%2F1%2Foriginal.20200728-184657?w=512&auto=format%2Ccompress&q=75&sharp=10&rect=0%2C0%2C800%2C400&s=fb4e1fc66a673a65f111539844a045da"
    },
    {
      "title": "Washington Crossing the Delaware / The Crossing - Film History Livestream",
      "date": "Upcoming",
      "location": "online",
      "link": "https://www.eventbrite.com/e/washington-crossing-the-delaware-the-crossing-film-history-livestream-tickets-1288476210029?aff=ebdssbcitybrowse",
      "image": "https://img.evbuc.com/https%3A%2F%2Fcdn.evbuc.com%2Fimages%2F536316699%2F37309396322%2F1%2Foriginal.20211020-221453?w=512&auto=format%2Ccompress&q=75&sharp=10&rect=0%2C422%2C6004%2C3002&s=f271b45ddf4bb7074a185f971f034a11"
    },
    {
      "title": "Tech In Terping",
      "date": "Upcoming",
      "location": "online",
      "link": "https://www.eventbrite.com/e/tech-in-terping-tickets-1980904301089?aff=ebdssbcitybrowse",
      "image": "https://img.evbuc.com/https%3A%2F%2Fcdn.evbuc.com%2Fimages%2F1020234643%2F1994693784923%2F1%2Foriginal.20250430-160751?crop=focalpoint&fit=crop&w=512&auto=format%2Ccompress&q=75&sharp=10&fp-x=0.191287878788&fp-y=0.449720670391&s=b33c944fab21d7025d440b3b972fc6b3"
    },
    {
      "title": "Researching your 20th century ancestors",
      "date": "Upcoming",
      "location": "online",
      "link": "https://www.eventbrite.co.uk/e/researching-your-20th-century-ancestors-tickets-1982962227402?aff=ebdssbcitybrowse",
      "image": "https://img.evbuc.com/https%3A%2F%2Fcdn.evbuc.com%2Fimages%2F1177365638%2F2824116931731%2F1%2Foriginal.20260212-114822?crop=focalpoint&fit=crop&w=512&auto=format%2Ccompress&q=75&sharp=10&fp-x=0.511&fp-y=0.707&s=f46e98ba812fa52546d00956c8fda3ad"
    },
    {
      "title": "Career Fair: Exclusive Tech Hiring Event-New Tickets Available",
      "date": "Upcoming",
      "location": "online",
      "link": "https://www.eventbrite.com/e/career-fair-exclusive-tech-hiring-event-new-tickets-available-tickets-63049080497?aff=ebdssbcitybrowse",
      "image": "https://img.evbuc.com/https%3A%2F%2Fcdn.evbuc.com%2Fimages%2F682597209%2F197361445633%2F1%2Foriginal.20240125-160053?w=512&auto=format%2Ccompress&q=75&sharp=10&rect=0%2C0%2C940%2C470&s=1790a7734766e877ae40e832f440984d"
    },
    {
      "title": "How to Do a  Venture Capital Financing",
      "date": "Upcoming",
      "location": "online",
      "link": "https://www.eventbrite.ca/e/how-to-do-a-venture-capital-financing-tickets-812165377507?aff=ebdssbcitybrowse",
      "image": "https://img.evbuc.com/https%3A%2F%2Fcdn.evbuc.com%2Fimages%2F485664049%2F3951017871%2F1%2Foriginal.20210122-000942?w=306&auto=format%2Ccompress&q=75&sharp=10&rect=4%2C0%2C306%2C153&s=ba5e43f03716796bdb9a171c845765cf"
    },
    {
      "title": "Grand Seafood Buffet - 29 March 2026",
      "date": "Upcoming",
      "location": "Sydney, NSW",
      "link": "https://www.eventbrite.com.au/e/grand-seafood-buffet-29-march-2026-tickets-1977851912312?aff=ebdssbcitybrowse",
      "image": "https://img.evbuc.com/https%3A%2F%2Fcdn.evbuc.com%2Fimages%2F1066444283%2F1283235757843%2F1%2Foriginal.20250704-010822?crop=focalpoint&fit=crop&w=512&auto=format%2Ccompress&q=75&sharp=10&fp-x=0.511885556308&fp-y=0.677481215875&s=d42ca3350b52c669d36524eac366698a"
    },
    {
      "title": "Paragon Fit presents the Cronulla Beach Fun Run/ Walk for Stroke Survivors",
      "date": "Upcoming",
      "location": "Cronulla, NSW",
      "link": "https://www.eventbrite.com.au/e/paragon-fit-presents-the-cronulla-beach-fun-run-walk-for-stroke-survivors-tickets-1983328217087?aff=ebdssbcitybrowse",
      "image": "https://img.evbuc.com/https%3A%2F%2Fcdn.evbuc.com%2Fimages%2F1177691130%2F2992369367723%2F1%2Foriginal.20260217-021601?w=512&auto=format%2Ccompress&q=75&sharp=10&rect=62%2C103%2C1370%2C685&s=21bd6e595fce27721c558e563c9ee768"
    },
    {
      "title": "Free Meditation - Uplift your wellbeing @ Dee Why , Sydney",
      "date": "Upcoming",
      "location": "Dee Why, NSW",
      "link": "https://www.eventbrite.com.au/e/free-meditation-uplift-your-wellbeing-dee-why-sydney-tickets-558630397557?aff=ebdssbcitybrowse",
      "image": "https://img.evbuc.com/https%3A%2F%2Fcdn.evbuc.com%2Fimages%2F820129559%2F206013995454%2F1%2Foriginal.20240804-080852?w=512&auto=format%2Ccompress&q=75&sharp=10&rect=0%2C23%2C4032%2C2016&s=be299265d0c71bf05323642ea8c9b401"
    },
    {
      "title": "Let's Meditate Sydney:  Free On-line Guided -Energy Awakening & Meditation",
      "date": "Upcoming",
      "location": "Sydney, NSW",
      "link": "https://www.eventbrite.com.au/e/lets-meditate-sydney-free-on-line-guided-energy-awakening-meditation-tickets-1444594303449?aff=ebdssbcitybrowse",
      "image": "https://img.evbuc.com/https%3A%2F%2Fcdn.evbuc.com%2Fimages%2F1062791423%2F2733633168271%2F1%2Foriginal.20250629-122849?crop=focalpoint&fit=crop&w=512&auto=format%2Ccompress&q=75&sharp=10&fp-x=0.489680363582&fp-y=0.0419723080917&s=305ed0d7bd0432117a60c02b58c4f2ec"
    },
    {
      "title": "lil.Sundays",
      "date": "Upcoming",
      "location": "North Bondi, NSW",
      "link": "https://www.eventbrite.nl/e/lilsundays-tickets-1983591122444?aff=ebdssbcitybrowse",
      "image": "https://img.evbuc.com/https%3A%2F%2Fcdn.evbuc.com%2Fimages%2F1177999060%2F287088142465%2F1%2Foriginal.20260220-031504?w=512&auto=format%2Ccompress&q=75&sharp=10&rect=0%2C946%2C1170%2C585&s=5488707525335d7f862a708b8e5fc191"
    },
    {
      "title": "Guided Meditation & Energy Healing",
      "date": "Upcoming",
      "location": "Curl Curl, NSW",
      "link": "https://www.eventbrite.com.au/e/guided-meditation-energy-healing-tickets-1979830748063?aff=ebdssbcitybrowse",
      "image": "https://img.evbuc.com/https%3A%2F%2Fcdn.evbuc.com%2Fimages%2F1172121982%2F1149778470783%2F1%2Foriginal.20251202-041306?crop=focalpoint&fit=crop&w=512&auto=format%2Ccompress&q=75&sharp=10&fp-x=0.5&fp-y=0.5&s=fdd4a716f8c43e585f83f3e3a32dc359"
    }
  ]
}