{
  "last_updated": "2026-05-31T08:46:20.397821Z",
  "events": [
    {
      "title": "Human vs Machine",
      "date": "Upcoming",
      "location": "Kensington, NSW",
      "link": "https://www.eventbrite.com.au/e/human-vs-machine-registration-1987576721478?aff=ebdssbneighborhoodbrowse",
      "image": "https://img.evbuc.com/https%3A%2F%2Fcdn.evbuc.com%2Fimages%2F1182838400%2F243879337343%2F1%2Foriginal.20260423-013848?crop=focalpoint&fit=crop&w=640&auto=format%2Ccompress&q=75&sharp=10&fp-x=0.5&fp-y=0.5&s=ef4050308c4aef11509d9931eebe4ea3"
    },
    {
      "title": "Retro Silent Disco | Vivid Season Special | Overseas Passenger Terminal",
      "date": "Upcoming",
      "location": "The Rocks, NSW",
      "link": "https://www.eventbrite.com/e/retro-silent-disco-vivid-season-special-overseas-passenger-terminal-tickets-1982192524199?aff=ebdssbneighborhoodbrowse",
      "image": "https://img.evbuc.com/https%3A%2F%2Fcdn.evbuc.com%2Fimages%2F1176458196%2F2526901173761%2F1%2Foriginal.20260202-153907?crop=focalpoint&fit=crop&w=640&auto=format%2Ccompress&q=75&sharp=10&fp-x=0.5&fp-y=0.5&s=55e51191a6755675b343072d0c1d192f"
    },
    {
      "title": "Sounds On Sunday - June Long Weekend 2026",
      "date": "Upcoming",
      "location": "North Sydney, NSW",
      "link": "https://www.eventbrite.com.au/e/sounds-on-sunday-june-long-weekend-2026-tickets-1982642744821?aff=ebdssbneighborhoodbrowse",
      "image": "https://img.evbuc.com/https%3A%2F%2Fcdn.evbuc.com%2Fimages%2F1177025563%2F246181746171%2F1%2Foriginal.20260209-012515?w=640&auto=format%2Ccompress&q=75&sharp=10&rect=0%2C0%2C2160%2C1080&s=f916f7d905800eabbfe3c5272e521063"
    },
    {
      "title": "HSC Workshop: Visual Arts - Written Exam Essentials",
      "date": "Upcoming",
      "location": "Marrickville, NSW",
      "link": "https://www.eventbrite.com.au/e/hsc-workshop-visual-arts-written-exam-essentials-tickets-1980606774178?aff=ebdssbneighborhoodbrowse",
      "image": "https://img.evbuc.com/https%3A%2F%2Fcdn.evbuc.com%2Fimages%2F1183299849%2F209095024738%2F1%2Foriginal.20260429-045232?crop=focalpoint&fit=crop&w=640&auto=format%2Ccompress&q=75&sharp=10&fp-x=0.5&fp-y=0.5&s=e95d30a51339c3d8e393e5d455d347af"
    },
    {
      "title": "GIROLOCO TOUR Presents: Naken @ Home The Venue Rooftop",
      "date": "Upcoming",
      "location": "Sydney, NSW",
      "link": "https://www.eventbrite.com/e/giroloco-tour-presents-naken-home-the-venue-rooftop-tickets-1988887552208?aff=ebdssbcitybrowsenightlife",
      "image": "https://img.evbuc.com/https%3A%2F%2Fcdn.evbuc.com%2Fimages%2F1184166968%2F2867609201311%2F1%2Foriginal.20260508-235728?crop=focalpoint&fit=crop&w=640&auto=format%2Ccompress&q=75&sharp=10&fp-x=0.96&fp-y=0.468&s=5015450bed981a5d339fb77b0d7b5963"
    },
    {
      "title": "Novel and Junkyard Present BAUGRUPPE90 & Lucas Boston",
      "date": "Upcoming",
      "location": "Sydney, NSW",
      "link": "https://www.eventbrite.com.au/e/novel-and-junkyard-present-baugruppe90-lucas-boston-tickets-1987976978658?aff=ebdssbcitybrowsenightlife",
      "image": "https://img.evbuc.com/https%3A%2F%2Fcdn.evbuc.com%2Fimages%2F1183178575%2F2522426015411%2F1%2Foriginal.20260428-001249?crop=focalpoint&fit=crop&w=640&auto=format%2Ccompress&q=75&sharp=10&fp-x=0.5&fp-y=0.5&s=ef50bab81fb85c6f682abaa40b90d750"
    },
    {
      "title": "Long Weekend Bollywood VIVID Cruise",
      "date": "Upcoming",
      "location": "Sydney, NSW",
      "link": "https://www.eventbrite.com.au/e/long-weekend-bollywood-vivid-cruise-tickets-1987308616569?aff=ebdssbcitybrowsenightlife",
      "image": "https://img.evbuc.com/https%3A%2F%2Fcdn.evbuc.com%2Fimages%2F1185397508%2F543158347683%2F1%2Foriginal.20260526-002923?crop=focalpoint&fit=crop&w=640&auto=format%2Ccompress&q=75&sharp=10&fp-x=0.5&fp-y=0.5&s=350dc50c0570f92af97daafbb5ab4937"
    },
    {
      "title": "HamilTown: Hamilton vs Hadestown Club Night - Sydney",
      "date": "Upcoming",
      "location": "Darling Park, NSW",
      "link": "https://www.eventbrite.com.au/e/hamiltown-hamilton-vs-hadestown-club-night-sydney-tickets-1988366119589?aff=ebdssbcitybrowsenightlife",
      "image": "https://img.evbuc.com/https%3A%2F%2Fcdn.evbuc.com%2Fimages%2F1183177644%2F2992588507035%2F1%2Foriginal.20260427-235454?w=640&auto=format%2Ccompress&q=75&sharp=10&s=e9fdce7051cb54ab30ebf57fcf0daf0e"
    },
    {
      "title": "Vivid Sydney Dinner Cruises | Buffet| Complimentary drink on arrival",
      "date": "Upcoming",
      "location": "Sydney, NSW",
      "link": "https://www.eventbrite.com.au/e/vivid-sydney-dinner-cruises-buffet-complimentary-drink-on-arrival-tickets-1985878777883?aff=ebdssbcitybrowse",
      "image": "https://img.evbuc.com/https%3A%2F%2Fcdn.evbuc.com%2Fimages%2F1184166946%2F157580943815%2F1%2Foriginal.20260508-235626?crop=focalpoint&fit=crop&h=230&w=460&auto=format%2Ccompress&q=75&sharp=10&fp-x=0.5&fp-y=0.5&s=b5daa26b845e8ec662ae816dc04eb7ff"
    },
    {
      "title": "Sea Gathering: Myth & Modernity",
      "date": "Upcoming",
      "location": "Sydney, NSW",
      "link": "https://www.eventbrite.com.au/e/sea-gathering-myth-modernity-tickets-1984356016262?aff=ebdssbcitybrowse",
      "image": "https://img.evbuc.com/https%3A%2F%2Fcdn.evbuc.com%2Fimages%2F1179343174%2F879630983583%2F1%2Foriginal.20260308-231543?w=640&auto=format%2Ccompress&q=75&sharp=10&rect=26%2C0%2C1800%2C900&s=2497de067ca296a01fe23e8c1471e0e8"
    },
    {
      "title": "FRI 05 JUN - LONG WEEKEND @ WAO SUPERCLUB",
      "date": "Upcoming",
      "location": "Sydney, NSW",
      "link": "https://www.eventbrite.com.au/e/fri-05-jun-long-weekend-wao-superclub-tickets-1988979738941?aff=ebdssbcitybrowse",
      "image": "https://img.evbuc.com/https%3A%2F%2Fcdn.evbuc.com%2Fimages%2F1183996592%2F1489176794133%2F1%2Foriginal.20260507-083842?crop=focalpoint&fit=crop&w=640&auto=format%2Ccompress&q=75&sharp=10&fp-x=0.5&fp-y=0.5&s=c972ecd724af554a37ce8d8cfa87a7e9"
    },
    {
      "title": "Homemade Saturdays: Free Entry + Complimentary Drink",
      "date": "Upcoming",
      "location": "Sydney, NSW",
      "link": "https://www.eventbrite.com.au/e/homemade-saturdays-free-entry-complimentary-drink-tickets-887309505617?aff=ebdssbcitybrowse",
      "image": "https://img.evbuc.com/https%3A%2F%2Fcdn.evbuc.com%2Fimages%2F1181761089%2F2055543935043%2F1%2Foriginal.20260409-072342?w=640&auto=format%2Ccompress&q=75&sharp=10&s=d1e2339d3f9812d26ab04a9e8aaa9bb3"
    },
    {
      "title": "Cargo Bar Saturdays x Bondi Lines | Free Entry",
      "date": "Upcoming",
      "location": "Sydney, NSW",
      "link": "https://www.eventbrite.com.au/e/cargo-bar-saturdays-x-bondi-lines-free-entry-tickets-1989265003174?aff=ebdssbcitybrowse",
      "image": "https://img.evbuc.com/https%3A%2F%2Fcdn.evbuc.com%2Fimages%2F1184344690%2F2050606160893%2F1%2Foriginal.20260511-222800?crop=focalpoint&fit=crop&w=640&auto=format%2Ccompress&q=75&sharp=10&fp-x=0.5&fp-y=0.5&s=1a2d3908ed74ddb38a28e7750cd7fc66"
    },
    {
      "title": "#BeerOps SYDNEY 2026 - Australia's Largest Tech Networking Event!",
      "date": "Upcoming",
      "location": "Sydney, NSW",
      "link": "https://www.eventbrite.com.au/e/beerops-sydney-2026-australias-largest-tech-networking-event-tickets-1967325136442?aff=ebdssbcitybrowse",
      "image": "https://img.evbuc.com/https%3A%2F%2Fcdn.evbuc.com%2Fimages%2F1180297669%2F33086941601%2F1%2Foriginal.20260320-054138?w=640&auto=format%2Ccompress&q=75&sharp=10&rect=1%2C251%2C3956%2C1978&s=8e82048f01c5dbb510194cc99ce7884e"
    },
    {
      "title": "Economic Outlook: Constructing Confidence in Uncertain Times",
      "date": "Upcoming",
      "location": "Sydney, NSW",
      "link": "https://www.eventbrite.com.au/e/economic-outlook-constructing-confidence-in-uncertain-times-tickets-1989456015497?aff=ebdssbcitybrowse",
      "image": "https://img.evbuc.com/https%3A%2F%2Fcdn.evbuc.com%2Fimages%2F1184573915%2F289529060115%2F1%2Foriginal.20260514-073856?crop=focalpoint&fit=crop&w=640&auto=format%2Ccompress&q=75&sharp=10&fp-x=0.5&fp-y=0.5&s=16065165809cfdf6688a0678e85a1043"
    },
    {
      "title": "Australian Tattoo Expo Sydney | 1,000 Tattoo Designs | HUGE Give-aways",
      "date": "Upcoming",
      "location": "Sydney, NSW",
      "link": "https://www.eventbrite.com.au/e/australian-tattoo-expo-sydney-1000-tattoo-designs-huge-give-aways-tickets-1982400187325?aff=ebdssbcitybrowse",
      "image": "https://img.evbuc.com/https%3A%2F%2Fcdn.evbuc.com%2Fimages%2F1182293480%2F2887446487041%2F1%2Foriginal.20260416-032937?crop=focalpoint&fit=crop&w=640&auto=format%2Ccompress&q=75&sharp=10&fp-x=0.5&fp-y=0.5&s=130ba6619a057a0b30753ffbf4bff4ec"
    },
    {
      "title": "Atelier en ligne Psycom : prise en main du Cosmos Mental",
      "date": "Upcoming",
      "location": "online",
      "link": "https://www.eventbrite.com/e/billets-atelier-en-ligne-psycom-prise-en-main-du-cosmos-mental-1967530469599?aff=ebdssbcitybrowse",
      "image": "https://img.evbuc.com/https%3A%2F%2Fcdn.evbuc.com%2Fimages%2F1171401151%2F1573312459803%2F1%2Foriginal.20251120-092547?w=640&auto=format%2Ccompress&q=75&sharp=10&rect=0%2C0%2C940%2C470&s=4ea69125440096c1249d689e46effd4c"
    },
    {
      "title": "Soir\u00e9e de M\u00e9diumnit\u00e9 & Voyance Collective (ZOOM)",
      "date": "Upcoming",
      "location": "online",
      "link": "https://www.eventbrite.ca/e/billets-soiree-de-mediumnite-voyance-collective-zoom-1988173155428?aff=ebdssbcitybrowse",
      "image": "https://img.evbuc.com/https%3A%2F%2Fcdn.evbuc.com%2Fimages%2F1182960071%2F1554786741223%2F1%2Foriginal.20260424-131132?w=640&auto=format%2Ccompress&q=75&sharp=10&s=419b9e0453ef0c30e687e08a36e7ea93"
    },
    {
      "title": "Femmes, \u00e9pargne et litt\u00e9ratie financi\u00e8re\u00a0: au-del\u00e0 des st\u00e9r\u00e9otypes",
      "date": "Upcoming",
      "location": "online",
      "link": "https://www.eventbrite.ca/e/billets-femmes-epargne-et-litteratie-financiere-au-dela-des-stereotypes-1987060487408?aff=ebdssbcitybrowse",
      "image": "https://img.evbuc.com/https%3A%2F%2Fcdn.evbuc.com%2Fimages%2F1182139183%2F2506842317821%2F1%2Foriginal.20260414-150447?crop=focalpoint&fit=crop&w=640&auto=format%2Ccompress&q=75&sharp=10&fp-x=0.09&fp-y=0.451&s=ffe14eb40330f68062392cbcbc040da9"
    },
    {
      "title": "Webinar : Estudios de caso y ense\u00f1anza del espa\u00f1ol profesional en Francia",
      "date": "Upcoming",
      "location": "online",
      "link": "https://www.eventbrite.fr/e/billets-webinar-estudios-de-caso-y-ensenanza-del-espanol-profesional-en-francia-1986206866204?aff=ebdssbcitybrowse",
      "image": "https://img.evbuc.com/https%3A%2F%2Fcdn.evbuc.com%2Fimages%2F1181765307%2F206916029802%2F1%2Foriginal.20260409-090410?w=640&auto=format%2Ccompress&q=75&sharp=10&s=b32e4e0e9834f77e1dad7cd2f35a4dfa"
    },
    {
      "title": "Caf\u00e9 virtuel Mission inclusion : Venez \u00e9changer avec Richard Veenstra, D.G",
      "date": "Upcoming",
      "location": "online",
      "link": "https://www.eventbrite.ca/e/billets-cafe-virtuel-mission-inclusion-venez-echanger-avec-richard-veenstra-dg-1989007054643?aff=ebdssbcitybrowse",
      "image": "https://img.evbuc.com/https%3A%2F%2Fcdn.evbuc.com%2Fimages%2F1184386274%2F166081957255%2F1%2Foriginal.20260512-114510?crop=focalpoint&fit=crop&w=640&auto=format%2Ccompress&q=75&sharp=10&fp-x=0.5&fp-y=0.5&s=5f3eec213ebd0c46b9f12324fe7f7f52"
    },
    {
      "title": "Live d\u00e9couverte : fili\u00e8re Cybers\u00e9curit\u00e9 - 11/06/26",
      "date": "Upcoming",
      "location": "online",
      "link": "https://www.eventbrite.fr/e/billets-live-decouverte-filiere-cybersecurite-110626-1990317259501?aff=ebdssbcitybrowse",
      "image": "https://img.evbuc.com/https%3A%2F%2Fcdn.evbuc.com%2Fimages%2F1185357823%2F473023403799%2F1%2Foriginal.20260525-114942?crop=focalpoint&fit=crop&w=640&auto=format%2Ccompress&q=75&sharp=10&fp-x=0.182&fp-y=0.558&s=a917217c4685114e0a7bed1589889df6"
    },
    {
      "title": "Espace de \u00a8Parole Parents- Surmonter les tensions dans le couple/babyclash",
      "date": "Upcoming",
      "location": "online",
      "link": "https://www.eventbrite.be/e/billets-espace-de-parole-parents-surmonter-les-tensions-dans-le-couplebabyclash-1987300653752?aff=ebdssbcitybrowse",
      "image": "https://img.evbuc.com/https%3A%2F%2Fcdn.evbuc.com%2Fimages%2F1182012516%2F497446881713%2F1%2Foriginal.20260413-083351?w=640&auto=format%2Ccompress&q=75&sharp=10&s=7f58d87d658e5decfbe5850bd2fbcc45"
    },
    {
      "title": "Processus d'admission \u00e0 l'OIQ pour les professionnels form\u00e9s \u00e0 l'\u00e9tranger",
      "date": "Upcoming",
      "location": "online",
      "link": "https://www.eventbrite.ca/e/billets-processus-dadmission-a-loiq-pour-les-professionnels-formes-a-letranger-1977628702686?aff=ebdssbcitybrowse",
      "image": "https://img.evbuc.com/https%3A%2F%2Fcdn.evbuc.com%2Fimages%2F1172781529%2F719379974233%2F1%2Foriginal.20250203-202258?w=640&auto=format%2Ccompress&q=75&sharp=10&rect=0%2C60%2C1920%2C960&s=8f7b1eaa87ffbfeaa4a8a46cbd6e9758"
    },
    {
      "title": "Vivid Sydney Rooftop Harbour Cruise + Free Fireworks Show",
      "date": "Upcoming",
      "location": "Circular Quay, NSW",
      "link": "https://www.eventbrite.com.au/e/vivid-sydney-rooftop-harbour-cruise-free-fireworks-show-tickets-1990094063917?aff=ebdssbcitybrowse",
      "image": "https://img.evbuc.com/https%3A%2F%2Fcdn.evbuc.com%2Fimages%2F1185752239%2F363582059739%2F1%2Foriginal.20260530-063502?crop=focalpoint&fit=crop&w=640&auto=format%2Ccompress&q=75&sharp=10&fp-x=0.496&fp-y=0.274&s=2483a1bfb35970c882daba1e4536426a"
    },
    {
      "title": "SYDNEY VIVID 2026 \u2013 DRONES +  LIGHTS SHOW",
      "date": "Upcoming",
      "location": "Sydney, NSW",
      "link": "https://www.eventbrite.com.au/e/sydney-vivid-2026-drones-lights-show-tickets-1987897334440?aff=ebdssbcitybrowse",
      "image": "https://img.evbuc.com/https%3A%2F%2Fcdn.evbuc.com%2Fimages%2F1184382806%2F2054205138613%2F1%2Foriginal.20260512-104323?crop=focalpoint&fit=crop&w=640&auto=format%2Ccompress&q=75&sharp=10&fp-x=0.514&fp-y=0.509&s=5f29de8d291734723c56dd5b7ffaf239"
    },
    {
      "title": "Live music photography at Tumbalong Park (Vivid Festival)",
      "date": "Upcoming",
      "location": "Sydney, NSW",
      "link": "https://www.eventbrite.com.au/e/live-music-photography-at-tumbalong-park-vivid-festival-tickets-1987868838207?aff=ebdssbcitybrowse",
      "image": "https://img.evbuc.com/https%3A%2F%2Fcdn.evbuc.com%2Fimages%2F1182617764%2F323118656843%2F1%2Foriginal.20260420-220506?crop=focalpoint&fit=crop&w=640&auto=format%2Ccompress&q=75&sharp=10&fp-x=0.121&fp-y=0.476&s=7de2549067391f42b1c9e208ee8e7d1d"
    },
    {
      "title": "Let's Meditate Sydney:  Free On-line Guided -Energy Awakening & Meditation",
      "date": "Upcoming",
      "location": "Sydney, NSW",
      "link": "https://www.eventbrite.com.au/e/lets-meditate-sydney-free-on-line-guided-energy-awakening-meditation-tickets-1444594303449?aff=ebdssbcitybrowse",
      "image": "https://img.evbuc.com/https%3A%2F%2Fcdn.evbuc.com%2Fimages%2F1062791423%2F2733633168271%2F1%2Foriginal.20250629-122849?crop=focalpoint&fit=crop&w=400&auto=format%2Ccompress&q=75&sharp=10&fp-x=0.489680363582&fp-y=0.0419723080917&s=5e360472b1887b8e3b3ea7c3a856735f"
    },
    {
      "title": "Luxury Vivid Sydney Experience 2026 // Oscar II Superyacht",
      "date": "Upcoming",
      "location": "Sydney, NSW",
      "link": "https://www.eventbrite.com.au/e/luxury-vivid-sydney-experience-2026-oscar-ii-superyacht-tickets-1983414669669?aff=ebdssbcitybrowse",
      "image": "https://img.evbuc.com/https%3A%2F%2Fcdn.evbuc.com%2Fimages%2F979450743%2F531815529893%2F1%2Foriginal.20250310-045807?w=640&auto=format%2Ccompress&q=75&sharp=10&rect=0%2C0%2C6794%2C3397&s=a4f274ad872b466bbd33bf0b94da16c3"
    },
    {
      "title": "Newtown Food & Street Art Small-Group Tour",
      "date": "Upcoming",
      "location": "Newtown, NSW",
      "link": "https://www.eventbrite.com.au/e/newtown-food-street-art-small-group-tour-tickets-98967750205?aff=ebdssbcitybrowse",
      "image": "https://img.evbuc.com/https%3A%2F%2Fcdn.evbuc.com%2Fimages%2F900942413%2F224304768850%2F1%2Foriginal.20241118-021407?w=640&auto=format%2Ccompress&q=75&sharp=10&rect=0%2C0%2C3308%2C1654&s=ac22aa6738c5e441fc4d394dc4589057"
    }
  ]
}