{
  "last_updated": "2026-03-07T12:49:57.221579Z",
  "events": [
    {
      "title": "Holi Festival Sydney - Darling Harbour -  8th March 2026",
      "date": "Upcoming",
      "location": "Sydney, NSW",
      "link": "https://www.eventbrite.com.au/e/holi-festival-sydney-darling-harbour-8th-march-2026-tickets-1977277916475?aff=ebdssbneighborhoodbrowse",
      "image": "https://img.evbuc.com/https%3A%2F%2Fcdn.evbuc.com%2Fimages%2F1172521241%2F36809088512%2F1%2Foriginal.20251208-133941?w=512&auto=format%2Ccompress&q=75&sharp=10&rect=0%2C0%2C1410%2C705&s=fed7ec3c765cc71cf4e0d7aa09eb2683"
    },
    {
      "title": "Make and Create: The Art of Kimchi & Fermentation with Marcea Klein",
      "date": "Upcoming",
      "location": "Marrickville, NSW",
      "link": "https://www.eventbrite.com.au/e/make-and-create-the-art-of-kimchi-fermentation-with-marcea-klein-tickets-1980691554759?aff=ebdssbneighborhoodbrowse",
      "image": "https://img.evbuc.com/https%3A%2F%2Fcdn.evbuc.com%2Fimages%2F1175203625%2F2504753628631%2F1%2Foriginal.20260119-010454?crop=focalpoint&fit=crop&auto=format%2Ccompress&q=75&sharp=10&fp-x=0.5&fp-y=0.5&s=8db7e2e4bd946f02d279f44aeee2f706"
    },
    {
      "title": "Sydney STEM Women Graduate Careers Event",
      "date": "Upcoming",
      "location": "Sydney, NSW",
      "link": "https://www.eventbrite.co.uk/e/sydney-stem-women-graduate-careers-event-tickets-1426964060919?aff=ebdssbneighborhoodbrowse",
      "image": "https://img.evbuc.com/https%3A%2F%2Fcdn.evbuc.com%2Fimages%2F1117325973%2F241549342757%2F1%2Foriginal.20250908-120958?w=512&auto=format%2Ccompress&q=75&sharp=10&rect=0%2C408%2C2160%2C1080&s=8815c572b5ec96797bd391fa4cee0e54"
    },
    {
      "title": "TALUM AUSTRALIA: Cafe Del Mar - Saturday 14th March 2026",
      "date": "Upcoming",
      "location": "Sydney, NSW",
      "link": "https://www.eventbrite.com/e/talum-australia-cafe-del-mar-saturday-14th-march-2026-tickets-1981930563668?aff=ebdssbneighborhoodbrowse",
      "image": "https://img.evbuc.com/https%3A%2F%2Fcdn.evbuc.com%2Fimages%2F1176151654%2F1469010098563%2F1%2Foriginal.20260129-120240?w=512&auto=format%2Ccompress&q=75&sharp=10&rect=0%2C171%2C2048%2C1024&s=7ef26239b1df43e333c9b01fb897de94"
    },
    {
      "title": "THE AFTERNOON SOIR\u00c9E: F1 EDITION",
      "date": "Upcoming",
      "location": "North Bondi, NSW",
      "link": "https://www.eventbrite.com.au/e/the-afternoon-soiree-f1-edition-tickets-1982945130264?aff=ebdssbcitybrowse",
      "image": "https://img.evbuc.com/https%3A%2F%2Fcdn.evbuc.com%2Fimages%2F1177700351%2F2987403535532%2F1%2Foriginal.20260217-051824?crop=focalpoint&fit=crop&h=230&w=460&auto=format%2Ccompress&q=75&sharp=10&fp-x=0.5&fp-y=0.5&s=2322355949b21ecf061e01003c4d4015"
    },
    {
      "title": "Homemade Saturdays: Free Entry + Complimentary Drink",
      "date": "Upcoming",
      "location": "Sydney, NSW",
      "link": "https://www.eventbrite.com.au/e/homemade-saturdays-free-entry-complimentary-drink-tickets-887309505617?aff=ebdssbcitybrowse",
      "image": "https://img.evbuc.com/https%3A%2F%2Fcdn.evbuc.com%2Fimages%2F748918359%2F2055543935043%2F1%2Foriginal.20240422-010025?w=512&auto=format%2Ccompress&q=75&sharp=10&rect=0%2C0%2C2160%2C1080&s=6de3c49714627a4ec6139403c1c4be75"
    },
    {
      "title": "Homemade Saturdays - 7th March 2026",
      "date": "Upcoming",
      "location": "Darling Park, NSW",
      "link": "https://www.eventbrite.com.au/e/homemade-saturdays-7th-march-2026-tickets-1979940919589?aff=ebdssbcitybrowse",
      "image": "https://img.evbuc.com/https%3A%2F%2Fcdn.evbuc.com%2Fimages%2F1178776219%2F245967499872%2F1%2Foriginal.20260302-105155?w=512&auto=format%2Ccompress&q=75&sharp=10&rect=0%2C60%2C1920%2C960&s=2d872a022fdf7d24c7d59a4d802b4d6a"
    },
    {
      "title": "Holi Festival Sydney - Darling Harbour -  8th March 2026",
      "date": "Upcoming",
      "location": "Sydney, NSW",
      "link": "https://www.eventbrite.com.au/e/holi-festival-sydney-darling-harbour-8th-march-2026-tickets-1977277916475?aff=ebdssbcitybrowse",
      "image": "https://img.evbuc.com/https%3A%2F%2Fcdn.evbuc.com%2Fimages%2F1172521241%2F36809088512%2F1%2Foriginal.20251208-133941?w=512&auto=format%2Ccompress&q=75&sharp=10&rect=0%2C0%2C1410%2C705&s=fed7ec3c765cc71cf4e0d7aa09eb2683"
    },
    {
      "title": "Sydney STEM Women Graduate Careers Event",
      "date": "Upcoming",
      "location": "Sydney, NSW",
      "link": "https://www.eventbrite.co.uk/e/sydney-stem-women-graduate-careers-event-tickets-1426964060919?aff=ebdssbcitybrowse",
      "image": "https://img.evbuc.com/https%3A%2F%2Fcdn.evbuc.com%2Fimages%2F1117325973%2F241549342757%2F1%2Foriginal.20250908-120958?w=512&auto=format%2Ccompress&q=75&sharp=10&rect=0%2C408%2C2160%2C1080&s=8815c572b5ec96797bd391fa4cee0e54"
    },
    {
      "title": "Engineering the Future: AI Evolving",
      "date": "Upcoming",
      "location": "Sydney, NSW",
      "link": "https://www.eventbrite.com.au/e/engineering-the-future-ai-evolving-registration-1983420665603?aff=ebdssbcitybrowse",
      "image": "https://img.evbuc.com/https%3A%2F%2Fcdn.evbuc.com%2Fimages%2F1177887963%2F243760117606%2F1%2Foriginal.20260218-230952?w=512&auto=format%2Ccompress&q=75&sharp=10&rect=0%2C0%2C2160%2C1080&s=4da3488ea9c3149b7ec3aee6f9a219ec"
    },
    {
      "title": "Lord Mayor\u2019s Welcome for International Students 2026",
      "date": "Upcoming",
      "location": "Sydney, NSW",
      "link": "https://www.eventbrite.com.au/e/lord-mayors-welcome-for-international-students-2026-tickets-1981065165238?aff=ebdssbcitybrowse",
      "image": "https://img.evbuc.com/https%3A%2F%2Fcdn.evbuc.com%2Fimages%2F1175396098%2F2421228637971%2F1%2Foriginal.20260120-230913?w=512&auto=format%2Ccompress&q=75&sharp=10&rect=0%2C443%2C3000%2C1500&s=1e7069e2ff490348f7f5eb57579aa121"
    },
    {
      "title": "em4. Sydney",
      "date": "Upcoming",
      "location": "Sydney, NSW",
      "link": "https://www.eventbrite.com.au/e/em4-sydney-tickets-1984447281238?aff=ebdssbcitybrowse",
      "image": "https://img.evbuc.com/https%3A%2F%2Fcdn.evbuc.com%2Fimages%2F1178983326%2F1797416342223%2F1%2Foriginal.20260304-061021?crop=focalpoint&fit=crop&w=512&auto=format%2Ccompress&q=75&sharp=10&fp-x=0.5&fp-y=0.5&s=9530cd513e77891245a6f54a3378caa6"
    },
    {
      "title": "Seminar on Big Data, Data Science and Machine Learning",
      "date": "Upcoming",
      "location": "online",
      "link": "https://www.eventbrite.com/e/seminar-on-big-data-data-science-and-machine-learning-tickets-787580734177?aff=ebdssbcitybrowse",
      "image": "https://img.evbuc.com/https%3A%2F%2Fcdn.evbuc.com%2Fimages%2F144527461%2F198476887449%2F1%2Foriginal.20200728-184657?w=512&auto=format%2Ccompress&q=75&sharp=10&rect=0%2C0%2C800%2C400&s=fb4e1fc66a673a65f111539844a045da"
    },
    {
      "title": "HBR Book Webinar:  The Transformation Economy",
      "date": "Upcoming",
      "location": "online",
      "link": "https://www.eventbrite.co.uk/e/hbr-book-webinar-the-transformation-economy-tickets-1980938915622?aff=ebdssbcitybrowse",
      "image": "https://img.evbuc.com/https%3A%2F%2Fcdn.evbuc.com%2Fimages%2F1175316209%2F24792341007%2F1%2Foriginal.20260120-081104?w=381&auto=format%2Ccompress&q=75&sharp=10&s=5ce5c83f2f784aebd3dfdfc803ed9b89"
    },
    {
      "title": "The Gut-Endo Reset",
      "date": "Upcoming",
      "location": "online",
      "link": "https://www.eventbrite.com.au/e/the-gut-endo-reset-tickets-1981509607577?aff=ebdssbcitybrowse",
      "image": "https://img.evbuc.com/https%3A%2F%2Fcdn.evbuc.com%2Fimages%2F1175752723%2F2206279418733%2F1%2Foriginal.20260125-041047?w=512&auto=format%2Ccompress&q=75&sharp=10&rect=0%2C291%2C2244%2C1122&s=a76b703899c74035c9cd09ef681be015"
    },
    {
      "title": "Preparing Young People (16\u201325) to Handle Money Confidently",
      "date": "Upcoming",
      "location": "online",
      "link": "https://www.eventbrite.co.uk/e/preparing-young-people-1625-to-handle-money-confidently-tickets-1983524146116?aff=ebdssbcitybrowse",
      "image": "https://img.evbuc.com/https%3A%2F%2Fcdn.evbuc.com%2Fimages%2F1177918554%2F2988130589532%2F1%2Foriginal.20260219-103441?crop=focalpoint&fit=crop&w=512&auto=format%2Ccompress&q=75&sharp=10&fp-x=0.5&fp-y=0.5&s=fe1effbabc356eac53d5cbd6320662f8"
    },
    {
      "title": "Career Fair: Exclusive Tech Hiring Event-New Tickets Available",
      "date": "Upcoming",
      "location": "online",
      "link": "https://www.eventbrite.com/e/career-fair-exclusive-tech-hiring-event-new-tickets-available-tickets-63049080497?aff=ebdssbcitybrowse",
      "image": "https://img.evbuc.com/https%3A%2F%2Fcdn.evbuc.com%2Fimages%2F682597209%2F197361445633%2F1%2Foriginal.20240125-160053?w=512&auto=format%2Ccompress&q=75&sharp=10&rect=0%2C0%2C940%2C470&s=1790a7734766e877ae40e832f440984d"
    },
    {
      "title": "Charlotte Hiring Event",
      "date": "Upcoming",
      "location": "online",
      "link": "https://www.eventbrite.com/e/charlotte-hiring-event-tickets-767132121827?aff=ebdssbcitybrowse",
      "image": "https://img.evbuc.com/https%3A%2F%2Fcdn.evbuc.com%2Fimages%2F648430759%2F109033103239%2F1%2Foriginal.20231126-234614?w=512&auto=format%2Ccompress&q=75&sharp=10&rect=1%2C519%2C4852%2C2426&s=eb795532ceb8af13be7d9fd1f9c1e7cf"
    },
    {
      "title": "Strengthening Parent-Youth Relationships: Managing Emotions",
      "date": "Upcoming",
      "location": "online",
      "link": "https://www.eventbrite.sg/e/strengthening-parent-youth-relationships-managing-emotions-tickets-1984112810828?aff=ebdssbcitybrowse",
      "image": "https://img.evbuc.com/https%3A%2F%2Fcdn.evbuc.com%2Fimages%2F1178976441%2F2993548776193%2F1%2Foriginal.20260304-032947?w=512&auto=format%2Ccompress&q=75&sharp=10&rect=0%2C0%2C2160%2C1080&s=6317f477b3474f6a0c727f29895dfd9a"
    },
    {
      "title": "Black Girl Book Fair!",
      "date": "Upcoming",
      "location": "online",
      "link": "https://www.eventbrite.com/e/black-girl-book-fair-tickets-1979838497241?aff=ebdssbcitybrowse",
      "image": "https://img.evbuc.com/https%3A%2F%2Fcdn.evbuc.com%2Fimages%2F1174070766%2F1007219303453%2F1%2Foriginal.20260106-030959?crop=focalpoint&fit=crop&w=512&auto=format%2Ccompress&q=75&sharp=10&fp-x=0.668&fp-y=0.597&s=56309c32964ceac8bd5e85c6431d5d2f"
    },
    {
      "title": "From Active Income to Lifelong Freedom",
      "date": "Upcoming",
      "location": "Sydney, NSW",
      "link": "https://www.eventbrite.com.au/e/from-active-income-to-lifelong-freedom-tickets-1980622277549?aff=ebdssbcitybrowse",
      "image": "https://img.evbuc.com/https%3A%2F%2Fcdn.evbuc.com%2Fimages%2F1174934299%2F137729330489%2F1%2Foriginal.20260115-093420?w=512&auto=format%2Ccompress&q=75&sharp=10&rect=0%2C0%2C1054%2C527&s=1032e42b66cdf98748f80dff45a9b6fa"
    },
    {
      "title": "Big Night Out Pub Crawl | FULL MOON PARTY | Saturday 7 March | Sydney",
      "date": "Upcoming",
      "location": "Sydney, NSW",
      "link": "https://www.eventbrite.com/e/big-night-out-pub-crawl-full-moon-party-saturday-7-march-sydney-tickets-1979709118265?aff=ebdssbcitybrowse",
      "image": "https://img.evbuc.com/https%3A%2F%2Fcdn.evbuc.com%2Fimages%2F853329429%2F154153969751%2F1%2Foriginal.20240918-133856?crop=focalpoint&fit=crop&w=512&auto=format%2Ccompress&q=75&sharp=10&fp-x=0.501893939394&fp-y=0.397009966777&s=ebc88f679677e503715cdedbfa42cb9d"
    },
    {
      "title": "**MEN SOLD OUT**\u26a1 SpeedAustralia Dating | Ages 25\u201339|Sydney's Modern Dating",
      "date": "Upcoming",
      "location": "Sydney, NSW",
      "link": "https://www.eventbrite.com/e/men-sold-out-speedaustralia-dating-ages-2539sydneys-modern-dating-tickets-1983331576134?aff=ebdssbcitybrowse",
      "image": "https://img.evbuc.com/https%3A%2F%2Fcdn.evbuc.com%2Fimages%2F1172348039%2F289603962789%2F1%2Foriginal.20251204-214413?w=314&auto=format%2Ccompress&q=75&sharp=10&s=59d962150d514a6bf157450733abe91d"
    },
    {
      "title": "SAT 7th March LIV IN THE DREAM SYDNEY NIGHTCLUB - Ladies Night Special",
      "date": "Upcoming",
      "location": "Sydney, NSW",
      "link": "https://www.eventbrite.com.au/e/sat-7th-march-liv-in-the-dream-sydney-nightclub-ladies-night-special-tickets-1984261294948?aff=ebdssbcitybrowse",
      "image": "https://img.evbuc.com/https%3A%2F%2Fcdn.evbuc.com%2Fimages%2F1178880092%2F2019243427853%2F1%2Foriginal.20260303-074512?w=400&auto=format%2Ccompress&q=75&sharp=10&s=356942e89b7de46ce83841f60a1d940e"
    },
    {
      "title": "Bollywood 'High Heels' at Indianclubx, Sydney",
      "date": "Upcoming",
      "location": "Sydney, NSW",
      "link": "https://www.eventbrite.com.au/e/bollywood-high-heels-at-indianclubx-sydney-tickets-1983061985782?aff=ebdssbcitybrowse",
      "image": "https://img.evbuc.com/https%3A%2F%2Fcdn.evbuc.com%2Fimages%2F1178603393%2F268079529119%2F1%2Foriginal.20260227-130620?w=512&auto=format%2Ccompress&q=75&sharp=10&rect=0%2C146%2C4100%2C2050&s=0f370ad6d1ba724225d2b84802c56296"
    },
    {
      "title": "Grand Seafood Buffet - 8 March 2026",
      "date": "Upcoming",
      "location": "Sydney, NSW",
      "link": "https://www.eventbrite.com.au/e/grand-seafood-buffet-8-march-2026-tickets-1977851709706?aff=ebdssbcitybrowse",
      "image": "https://img.evbuc.com/https%3A%2F%2Fcdn.evbuc.com%2Fimages%2F1066444283%2F1283235757843%2F1%2Foriginal.20250704-010822?crop=focalpoint&fit=crop&w=512&auto=format%2Ccompress&q=75&sharp=10&fp-x=0.511885556308&fp-y=0.677481215875&s=d42ca3350b52c669d36524eac366698a"
    },
    {
      "title": "La Femme | Women in Whisky Tasting",
      "date": "Upcoming",
      "location": "Sydney, NSW",
      "link": "https://www.eventbrite.com.au/e/la-femme-women-in-whisky-tasting-tickets-1982336468741?aff=ebdssbcitybrowse",
      "image": "https://img.evbuc.com/https%3A%2F%2Fcdn.evbuc.com%2Fimages%2F1176646531%2F268773832458%2F1%2Foriginal.20260204-061544?w=512&auto=format%2Ccompress&q=75&sharp=10&rect=0%2C0%2C1200%2C600&s=3a735dbf28fecbe63a5e09f471fede3e"
    }
  ]
}