{
  "last_updated": "2025-09-13T06:25:10.892743Z",
  "events": [
    {
      "title": "Realm of House | Sydney's Ultimate House Music Boat Party | Le Bleu",
      "date": "Upcoming",
      "location": "Pyrmont, NSW",
      "link": "https://www.eventbrite.com.au/e/realm-of-house-sydneys-ultimate-house-music-boat-party-le-bleu-tickets-1420167221389?aff=ebdssbneighborhoodbrowse",
      "image": "https://img.evbuc.com/https%3A%2F%2Fcdn.evbuc.com%2Fimages%2F1056299823%2F2633241269991%2F1%2Foriginal.20250619-031335?w=512&auto=format%2Ccompress&q=75&sharp=10&rect=0%2C0%2C2160%2C1080&s=e54a5f927e5d32b6cc2a2037e4859846"
    },
    {
      "title": "Darlinghurst clothes swap",
      "date": "Upcoming",
      "location": "Darlinghurst, NSW",
      "link": "https://www.eventbrite.com.au/e/darlinghurst-clothes-swap-tickets-1514623442489?aff=ebdssbneighborhoodbrowse",
      "image": "https://img.evbuc.com/https%3A%2F%2Fcdn.evbuc.com%2Fimages%2F1106229343%2F1543550715783%2F1%2Foriginal.20250827-060008?w=512&auto=format%2Ccompress&q=75&sharp=10&rect=1%2C557%2C6918%2C3459&s=85413f56818d819e161e31d811740953"
    },
    {
      "title": "240km/h F2F Sydney",
      "date": "Upcoming",
      "location": "Sydney, NSW",
      "link": "https://www.eventbrite.com.au/e/240kmh-f2f-sydney-tickets-1498316959359?aff=ebdssbneighborhoodbrowse",
      "image": "https://img.evbuc.com/https%3A%2F%2Fcdn.evbuc.com%2Fimages%2F1079451643%2F564171898029%2F1%2Foriginal.20250723-075855?w=512&auto=format%2Ccompress&q=75&sharp=10&rect=0%2C0%2C2160%2C1080&s=445b6b5883d8f0c152fb4d4a71b669c9"
    },
    {
      "title": "DJ Snoopadelic (AKA Snoop Dogg)",
      "date": "Upcoming",
      "location": "Sydney, NSW",
      "link": "https://www.eventbrite.com.au/e/dj-snoopadelic-aka-snoop-dogg-tickets-1633177520929?aff=ebdssbneighborhoodbrowse",
      "image": "https://img.evbuc.com/https%3A%2F%2Fcdn.evbuc.com%2Fimages%2F1106260773%2F383685795655%2F1%2Foriginal.20250827-074107?crop=focalpoint&fit=crop&auto=format%2Ccompress&q=75&sharp=10&fp-x=0.494208494208&fp-y=0.505084745763&s=6366964eac8f99a41b21810b123f9957"
    },
    {
      "title": "SUNDAYLICIOUS SYDNEY |  SAT NIGHT | SEP 13 | 9pm - 3am | LGBTQIA+ event",
      "date": "Upcoming",
      "location": "Sydney, NSW",
      "link": "https://www.eventbrite.com.au/e/sundaylicious-sydney-sat-night-sep-13-9pm-3am-lgbtqia-event-tickets-1420957946469?aff=ebdssbcitybrowsenightlife",
      "image": "https://img.evbuc.com/https%3A%2F%2Fcdn.evbuc.com%2Fimages%2F1056436333%2F363534760949%2F1%2Foriginal.20250619-100049?w=400&auto=format%2Ccompress&q=75&sharp=10&s=bc2a3ce439f5e968eb9219bce8af7744"
    },
    {
      "title": "FRI 19 SEP - BEAUZ @ WAO SUPERCLUB",
      "date": "Upcoming",
      "location": "Sydney, NSW",
      "link": "https://www.eventbrite.com.au/e/fri-19-sep-beauz-wao-superclub-tickets-1543161430379?aff=ebdssbcitybrowsenightlife",
      "image": "https://img.evbuc.com/https%3A%2F%2Fcdn.evbuc.com%2Fimages%2F1084215543%2F713796481473%2F1%2Foriginal.20250730-034405?h=200&w=512&auto=format%2Ccompress&q=75&sharp=10&rect=0%2C0%2C2160%2C1080&s=25e66c2ff8ad9172f41d59f990dcdad0"
    },
    {
      "title": "Sublime Reunion 2025",
      "date": "Upcoming",
      "location": "Darling Park, NSW",
      "link": "https://www.eventbrite.com.au/e/sublime-reunion-2025-tickets-1388676451649?aff=ebdssbcitybrowsenightlife",
      "image": "https://img.evbuc.com/https%3A%2F%2Fcdn.evbuc.com%2Fimages%2F1072738993%2F245967499872%2F1%2Foriginal.20250714-032649?w=512&auto=format%2Ccompress&q=75&sharp=10&rect=0%2C0%2C1920%2C960&s=857f9e085aa3d74cbc9ef9c7b2346b19"
    },
    {
      "title": "BERLIN RAVE (Sydney) ft  KOBOSIL (DE) & UEBERREST (DE)",
      "date": "Upcoming",
      "location": "Sydney, NSW",
      "link": "https://www.eventbrite.com.au/e/berlin-rave-sydney-ft-kobosil-de-ueberrest-de-tickets-1570740018679?aff=ebdssbcitybrowsenightlife",
      "image": "https://img.evbuc.com/https%3A%2F%2Fcdn.evbuc.com%2Fimages%2F1102559233%2F347014776913%2F1%2Foriginal.20250822-122938?w=512&auto=format%2Ccompress&q=75&sharp=10&rect=0%2C58%2C1920%2C960&s=58d51d4a3ba958627086a4e4200e6792"
    },
    {
      "title": "Bond Carnage vs Risk Rally: The Great Disconnect",
      "date": "Upcoming",
      "location": "Sydney, NSW",
      "link": "https://www.eventbrite.com.au/e/bond-carnage-vs-risk-rally-the-great-disconnect-tickets-1685838641759?aff=ebdssbcitybrowse",
      "image": "https://img.evbuc.com/https%3A%2F%2Fcdn.evbuc.com%2Fimages%2F1120755623%2F2610370316201%2F1%2Foriginal.20250911-022703?crop=focalpoint&fit=crop&h=230&w=460&auto=format%2Ccompress&q=75&sharp=10&fp-x=0.00928661577629&fp-y=0.00544776119403&s=6637a71053a37c577c8df5d68c452762"
    },
    {
      "title": "Quintal Sydney 12 edition",
      "date": "Upcoming",
      "location": "Coogee, NSW",
      "link": "https://www.eventbrite.com.au/e/quintal-sydney-12-edition-tickets-1412525865889?aff=ebdssbcitybrowse",
      "image": "https://img.evbuc.com/https%3A%2F%2Fcdn.evbuc.com%2Fimages%2F1053742723%2F900199079423%2F1%2Foriginal.20250616-103031?w=512&auto=format%2Ccompress&q=75&sharp=10&rect=0%2C0%2C2160%2C1080&s=d2277d74ed56ecaa2f9104cc9a5b54d1"
    },
    {
      "title": "Homemade Saturdays: Free Entry + Complimentary Drink",
      "date": "Upcoming",
      "location": "Sydney, NSW",
      "link": "https://www.eventbrite.com.au/e/homemade-saturdays-free-entry-complimentary-drink-tickets-887309505617?aff=ebdssbcitybrowse",
      "image": "https://img.evbuc.com/https%3A%2F%2Fcdn.evbuc.com%2Fimages%2F748918359%2F2055543935043%2F1%2Foriginal.20240422-010025?h=200&w=512&auto=format%2Ccompress&q=75&sharp=10&rect=0%2C0%2C2160%2C1080&s=32bfbc6b9a2b8f1a76dc8e6b68f0c9e8"
    },
    {
      "title": "SECOND LIFE ARCHIVE: Sydney Sept 14th",
      "date": "Upcoming",
      "location": "Sydney, NSW",
      "link": "https://www.eventbrite.com.au/e/second-life-archive-sydney-sept-14th-tickets-1582224418829?aff=ebdssbcitybrowse",
      "image": "https://img.evbuc.com/https%3A%2F%2Fcdn.evbuc.com%2Fimages%2F1110429313%2F1632322136163%2F1%2Foriginal.20250901-101340?h=200&w=512&auto=format%2Ccompress&q=75&sharp=10&s=1e27e9e4412fa07341b186e7c8a3f61a"
    },
    {
      "title": "FRI 26 SEP - WAO SUPERCLUB @ IVY",
      "date": "Upcoming",
      "location": "Sydney, NSW",
      "link": "https://www.eventbrite.com.au/e/fri-26-sep-wao-superclub-ivy-tickets-1559343511419?aff=ebdssbcitybrowse",
      "image": "https://img.evbuc.com/https%3A%2F%2Fcdn.evbuc.com%2Fimages%2F1088535723%2F713796481473%2F1%2Foriginal.20250805-120200?w=512&auto=format%2Ccompress&q=75&sharp=10&rect=0%2C0%2C2160%2C1080&s=6d11b93400f89ded18984509b9860ab9"
    },
    {
      "title": "DJ Snoopadelic (AKA Snoop Dogg)",
      "date": "Upcoming",
      "location": "Sydney, NSW",
      "link": "https://www.eventbrite.com.au/e/dj-snoopadelic-aka-snoop-dogg-tickets-1633177520929?aff=ebdssbcitybrowse",
      "image": "https://img.evbuc.com/https%3A%2F%2Fcdn.evbuc.com%2Fimages%2F1106260773%2F383685795655%2F1%2Foriginal.20250827-074107?crop=focalpoint&fit=crop&w=512&auto=format%2Ccompress&q=75&sharp=10&fp-x=0.494208494208&fp-y=0.505084745763&s=f4be3829a5eae6f5cdd4d521f45280a1"
    },
    {
      "title": "The Spirit of Diwali Sydney 2025 (Free Entry Tickets)",
      "date": "Upcoming",
      "location": "Sydney, NSW",
      "link": "https://www.eventbrite.com.au/e/the-spirit-of-diwali-sydney-2025-free-entry-tickets-tickets-1539897076609?aff=ebdssbcitybrowse",
      "image": "https://img.evbuc.com/https%3A%2F%2Fcdn.evbuc.com%2Fimages%2F1117162623%2F2848445205851%2F1%2Foriginal.20250908-075249?crop=focalpoint&fit=crop&w=400&auto=format%2Ccompress&q=75&sharp=10&fp-x=0.479732920823&fp-y=0.0217898773312&s=f5841ee36a11e559b48bf1a6efdf578d"
    },
    {
      "title": "Family Fun Day | Free Event",
      "date": "Upcoming",
      "location": "Sydney, NSW",
      "link": "https://www.eventbrite.com.au/e/family-fun-day-free-event-tickets-1329207227599?aff=ebdssbcitybrowse",
      "image": "https://img.evbuc.com/https%3A%2F%2Fcdn.evbuc.com%2Fimages%2F1106036853%2F512094176045%2F1%2Foriginal.20250827-000219?w=512&auto=format%2Ccompress&q=75&sharp=10&rect=0%2C0%2C2160%2C1080&s=affe36769b4dc22b9e1e6332ce9ff927"
    },
    {
      "title": "NASA's Northrop Grumman CRS-23 Launch",
      "date": "Upcoming",
      "location": "online",
      "link": "https://www.eventbrite.com/e/nasas-northrop-grumman-crs-23-launch-registration-1587433579569?aff=ebdssbcitybrowse",
      "image": "https://img.evbuc.com/https%3A%2F%2Fcdn.evbuc.com%2Fimages%2F470921289%2F435332337358%2F1%2Foriginal.20220119-164608?h=200&w=512&auto=format%2Ccompress&q=75&sharp=10&rect=114%2C97%2C1062%2C531&s=f91c77c5f0490117f21056dae50aebf7"
    },
    {
      "title": "Amplified 2025",
      "date": "Upcoming",
      "location": "online",
      "link": "https://www.eventbrite.com/e/amplified-2025-tickets-1482812615449?aff=ebdssbcitybrowse",
      "image": "https://img.evbuc.com/https%3A%2F%2Fcdn.evbuc.com%2Fimages%2F1073733943%2F1128558171253%2F1%2Foriginal.20250715-085118?w=512&auto=format%2Ccompress&q=75&sharp=10&rect=0%2C0%2C2160%2C1080&s=dfc8f9c2e2f17888fe3442bda472b1d1"
    },
    {
      "title": "HBR Press Webinar:  Epic Disruptions",
      "date": "Upcoming",
      "location": "online",
      "link": "https://www.eventbrite.com/e/hbr-press-webinar-epic-disruptions-tickets-1542431256409?aff=ebdssbcitybrowse",
      "image": "https://img.evbuc.com/https%3A%2F%2Fcdn.evbuc.com%2Fimages%2F1083705713%2F24792341007%2F1%2Foriginal.20250729-162108?w=512&auto=format%2Ccompress&q=75&sharp=10&rect=0%2C15%2C1200%2C600&s=d5af9284bba5de81056ffb9d96e2116e"
    },
    {
      "title": "HBR Book Webinar: Epic Disruptions",
      "date": "Upcoming",
      "location": "online",
      "link": "https://www.eventbrite.co.uk/e/hbr-book-webinar-epic-disruptions-tickets-1538317742779?aff=ebdssbcitybrowse",
      "image": "https://img.evbuc.com/https%3A%2F%2Fcdn.evbuc.com%2Fimages%2F1082952653%2F24792341007%2F1%2Foriginal.20250728-191433?w=512&auto=format%2Ccompress&q=75&sharp=10&rect=0%2C15%2C1200%2C600&s=09d4c4d47eec049dad1fd058610c63ad"
    },
    {
      "title": "Career Fair: Exclusive Tech Hiring Event-New Tickets Available",
      "date": "Upcoming",
      "location": "online",
      "link": "https://www.eventbrite.com/e/career-fair-exclusive-tech-hiring-event-new-tickets-available-tickets-63049080497?aff=ebdssbcitybrowse",
      "image": "https://img.evbuc.com/https%3A%2F%2Fcdn.evbuc.com%2Fimages%2F682597209%2F197361445633%2F1%2Foriginal.20240125-160053?w=512&auto=format%2Ccompress&q=75&sharp=10&rect=0%2C0%2C940%2C470&s=1790a7734766e877ae40e832f440984d"
    },
    {
      "title": "No Cost On-Line Coursera Certification Courses For Military and Spouse",
      "date": "Upcoming",
      "location": "online",
      "link": "https://www.eventbrite.com/e/no-cost-on-line-coursera-certification-courses-for-military-and-spouse-tickets-165655358637?aff=ebdssbcitybrowse",
      "image": "https://img.evbuc.com/https%3A%2F%2Fcdn.evbuc.com%2Fimages%2F631748609%2F122310519079%2F1%2Foriginal.20231031-040429?h=200&w=512&auto=format%2Ccompress&q=75&sharp=10&rect=0%2C0%2C2160%2C1080&s=9765e1463a5fb166a5156497ff84f70d"
    },
    {
      "title": "Nuovo Regolamento Imballaggi",
      "date": "Upcoming",
      "location": "online",
      "link": "https://www.eventbrite.com/e/nuovo-regolamento-imballaggi-tickets-1555518921969?aff=ebdssbcitybrowse",
      "image": "https://img.evbuc.com/https%3A%2F%2Fcdn.evbuc.com%2Fimages%2F1088408723%2F482120100033%2F1%2Foriginal.20250805-072247?w=400&auto=format%2Ccompress&q=75&sharp=10&s=66553415462cfa349a6786cdc238f4b8"
    },
    {
      "title": "Research Learning Lectures",
      "date": "Upcoming",
      "location": "online",
      "link": "https://www.eventbrite.com/e/research-learning-lectures-tickets-472469798887?aff=ebdssbcitybrowse",
      "image": "https://img.evbuc.com/https%3A%2F%2Fcdn.evbuc.com%2Fimages%2F632630769%2F583901517333%2F1%2Foriginal.20231101-092848?h=200&w=512&auto=format%2Ccompress&q=75&sharp=10&rect=0%2C0%2C2160%2C1080&s=f34955091d24b07dcf184f1092458a57"
    },
    {
      "title": "History Week: Go toward the Light! The Lighthouse in the middle of Sydney",
      "date": "Upcoming",
      "location": "Sydney, NSW",
      "link": "https://www.eventbrite.com.au/e/history-week-go-toward-the-light-the-lighthouse-in-the-middle-of-sydney-tickets-1298761654069?aff=ebdssbcitybrowse",
      "image": "https://img.evbuc.com/https%3A%2F%2Fcdn.evbuc.com%2Fimages%2F990842503%2F679473379903%2F1%2Foriginal.20250324-031957?w=307&auto=format%2Ccompress&q=75&sharp=10&s=9bc1683d5c2b5678e5bc34c8a9f1b5c0"
    },
    {
      "title": "SUNDAYLICIOUS SYDNEY |  SAT NIGHT | SEP 13 | 9pm - 3am | LGBTQIA+ event",
      "date": "Upcoming",
      "location": "Sydney, NSW",
      "link": "https://www.eventbrite.com.au/e/sundaylicious-sydney-sat-night-sep-13-9pm-3am-lgbtqia-event-tickets-1420957946469?aff=ebdssbcitybrowse",
      "image": "https://img.evbuc.com/https%3A%2F%2Fcdn.evbuc.com%2Fimages%2F1056436333%2F363534760949%2F1%2Foriginal.20250619-100049?w=400&auto=format%2Ccompress&q=75&sharp=10&s=bc2a3ce439f5e968eb9219bce8af7744"
    },
    {
      "title": "Rhinestone Rodeo - Line dancing class at Cronulla Surf Club",
      "date": "Upcoming",
      "location": "Cronulla, NSW",
      "link": "https://www.eventbrite.com/e/rhinestone-rodeo-line-dancing-class-at-cronulla-surf-club-tickets-1641376945629?aff=ebdssbcitybrowse",
      "image": "https://img.evbuc.com/https%3A%2F%2Fcdn.evbuc.com%2Fimages%2F1098186363%2F2867471967351%2F1%2Foriginal.20250818-043720?crop=focalpoint&fit=crop&w=512&auto=format%2Ccompress&q=75&sharp=10&fp-x=0.493371212121&fp-y=0.51593625498&s=94d87b794ff3b4c40b96497c4f993c0b"
    },
    {
      "title": "Senpo Photowalk",
      "date": "Upcoming",
      "location": "Sydney, NSW",
      "link": "https://www.eventbrite.com.au/e/senpo-photowalk-tickets-1588667018819?aff=ebdssbcitybrowse",
      "image": "https://img.evbuc.com/https%3A%2F%2Fcdn.evbuc.com%2Fimages%2F1095507443%2F1755117891283%2F1%2Foriginal.20250814-053903?crop=focalpoint&fit=crop&w=512&auto=format%2Ccompress&q=75&sharp=10&fp-x=5e-05&fp-y=5e-05&s=6d20b2c3baa81672ac21cf3050c017e8"
    },
    {
      "title": "BOLLY AFRO night at Cheers nightclub, Sydney",
      "date": "Upcoming",
      "location": "Sydney, NSW",
      "link": "https://www.eventbrite.com.au/e/bolly-afro-night-at-cheers-nightclub-sydney-tickets-1568959513139?aff=ebdssbcitybrowse",
      "image": "https://img.evbuc.com/https%3A%2F%2Fcdn.evbuc.com%2Fimages%2F1091133523%2F1581357987003%2F1%2Foriginal.20250808-064425?crop=focalpoint&fit=crop&w=401&auto=format%2Ccompress&q=75&sharp=10&fp-x=0.00501893939394&fp-y=0.00524253731343&s=5bd4d0f38183a52871d0e43315c517b7"
    },
    {
      "title": "Fast Friending: Meet like-minded ladies & gents! (21-45/Happy Hours)SYD",
      "date": "Upcoming",
      "location": "Sydney, NSW",
      "link": "https://www.eventbrite.co.uk/e/fast-friending-meet-like-minded-ladies-gents-21-45happy-hourssyd-tickets-1624077402229?aff=ebdssbcitybrowse",
      "image": "https://img.evbuc.com/https%3A%2F%2Fcdn.evbuc.com%2Fimages%2F1103221463%2F285552070707%2F1%2Foriginal.20250105-110504?w=512&auto=format%2Ccompress&q=75&sharp=10&rect=0%2C200%2C1600%2C800&s=14cc2c5f83b618d623f12eb09f791265"
    },
    {
      "title": "Around the World with Bunnik Tours | Sydney",
      "date": "Upcoming",
      "location": "Sydney, NSW",
      "link": "https://www.eventbrite.com.au/e/around-the-world-with-bunnik-tours-sydney-tickets-1555006288669?aff=ebdssbcitybrowse",
      "image": "https://img.evbuc.com/https%3A%2F%2Fcdn.evbuc.com%2Fimages%2F1088307403%2F211538856646%2F1%2Foriginal.20250805-023808?w=400&auto=format%2Ccompress&q=75&sharp=10&s=dd2ebf346dc2de60d8ecabfa706a212c"
    },
    {
      "title": "xHale: Shamanic Breathwork Journey",
      "date": "Upcoming",
      "location": "North Bondi, NSW",
      "link": "https://www.eventbrite.com.au/e/xhale-shamanic-breathwork-journey-tickets-1489763034339?aff=ebdssbcitybrowse",
      "image": "https://img.evbuc.com/https%3A%2F%2Fcdn.evbuc.com%2Fimages%2F1073658333%2F90676474057%2F1%2Foriginal.20250715-050138?w=400&auto=format%2Ccompress&q=75&sharp=10&s=a90aa1876e2719bf069cb655284e1eb4"
    }
  ]
}