{
  "last_updated": "2025-07-26T12:40:14.938074Z",
  "events": [
    {
      "title": "Dykadellic - The Ultimate Lesbian Day Party @Botany | Sat 26 July 2025",
      "date": "Upcoming",
      "location": "Newtown, NSW",
      "link": "https://www.eventbrite.com.au/e/dykadellic-the-ultimate-lesbian-day-party-botany-view-sat-26-july-2025-tickets-1383222940049?aff=ebdssbneighborhoodbrowse",
      "image": "https://img.evbuc.com/https%3A%2F%2Fcdn.evbuc.com%2Fimages%2F1040279243%2F2605489477831%2F1%2Foriginal.20250528-022232?crop=focalpoint&fit=crop&auto=format%2Ccompress&q=75&sharp=10&fp-x=0.496138996139&fp-y=0.894555865181&s=68274f6cb1ed9cc5fe1e8f2cfb5b267c"
    },
    {
      "title": "Prime Book Club LIVE",
      "date": "Upcoming",
      "location": "Sydney, NSW",
      "link": "https://www.eventbrite.com/e/prime-book-club-live-tickets-1475438037889?aff=ebdssbneighborhoodbrowse",
      "image": "https://img.evbuc.com/https%3A%2F%2Fcdn.evbuc.com%2Fimages%2F1069620843%2F2821635492401%2F1%2Foriginal.20250709-053856?crop=focalpoint&fit=crop&auto=format%2Ccompress&q=75&sharp=10&fp-x=0.433712121212&fp-y=0.479553903346&s=3d56e52481702f6b8a545a97e1340e25"
    },
    {
      "title": "IN PERSON Skirts on Sacred Benches: 100 years of women in NSW Parliament",
      "date": "Upcoming",
      "location": "Sydney, NSW",
      "link": "https://www.eventbrite.com.au/e/in-person-skirts-on-sacred-benches-100-years-of-women-in-nsw-parliament-tickets-1448276115849?aff=ebdssbneighborhoodbrowse",
      "image": "https://img.evbuc.com/https%3A%2F%2Fcdn.evbuc.com%2Fimages%2F1063871943%2F512094176045%2F1%2Foriginal.20250701-013800?w=512&auto=format%2Ccompress&q=75&sharp=10&rect=0%2C0%2C2160%2C1080&s=6d47086ba42e5bd4efbad18427a5581d"
    },
    {
      "title": "AI Hack Day - Sydney",
      "date": "Upcoming",
      "location": "Sydney, NSW",
      "link": "https://www.eventbrite.com.au/e/ai-hack-day-sydney-tickets-1217361263309?aff=ebdssbneighborhoodbrowse",
      "image": "https://img.evbuc.com/https%3A%2F%2Fcdn.evbuc.com%2Fimages%2F524370099%2F55525066651%2F1%2Foriginal.20230529-052632?w=512&auto=format%2Ccompress&q=75&sharp=10&rect=0%2C0%2C2160%2C1080&s=86fb5e3fa45a940a0db7bcbcfae491fb"
    },
    {
      "title": "Plaza Basement x Motive Records Takeover",
      "date": "Upcoming",
      "location": "Sydney, NSW",
      "link": "https://www.eventbrite.com/e/plaza-basement-x-motive-records-takeover-tickets-1365257876059?aff=ebdssbcitybrowsenightlife",
      "image": "https://img.evbuc.com/https%3A%2F%2Fcdn.evbuc.com%2Fimages%2F1035469703%2F2530488701891%2F1%2Foriginal.20250520-235255?crop=focalpoint&fit=crop&w=512&auto=format%2Ccompress&q=75&sharp=10&fp-x=0.948863636364&fp-y=0.498220640569&s=0fe49ed7f28cd143d77ebe268852f843"
    },
    {
      "title": "CRAVE feat. PAUL VAN DYK",
      "date": "Upcoming",
      "location": "Sydney, NSW",
      "link": "https://www.eventbrite.com.au/e/crave-feat-paul-van-dyk-tickets-1425038952869?aff=ebdssbcitybrowsenightlife",
      "image": "https://img.evbuc.com/https%3A%2F%2Fcdn.evbuc.com%2Fimages%2F1057654233%2F566220113875%2F1%2Foriginal.20250621-011217?w=512&auto=format%2Ccompress&q=75&sharp=10&rect=0%2C73%2C1920%2C960&s=198f6ab0525410ee452612e6c3c148f8"
    },
    {
      "title": "The Country Superstar Experience - Sydney",
      "date": "Upcoming",
      "location": "Darling Park, NSW",
      "link": "https://www.eventbrite.com.au/e/the-country-superstar-experience-sydney-tickets-1319549019639?aff=ebdssbcitybrowsenightlife",
      "image": "https://img.evbuc.com/https%3A%2F%2Fcdn.evbuc.com%2Fimages%2F1005467703%2F2245701384243%2F1%2Foriginal.20250410-012609?crop=focalpoint&fit=crop&auto=format%2Ccompress&q=75&sharp=10&fp-x=0.5&fp-y=0.5&s=49e99b27bf97285728458e09c1e0c5f9"
    },
    {
      "title": "Underground Funk",
      "date": "Upcoming",
      "location": "Sydney, NSW",
      "link": "https://www.eventbrite.com/e/underground-funk-tickets-1397572289339?aff=ebdssbcitybrowsenightlife",
      "image": "https://img.evbuc.com/https%3A%2F%2Fcdn.evbuc.com%2Fimages%2F1046332713%2F275680237230%2F1%2Foriginal.20250605-034115?crop=focalpoint&fit=crop&w=512&auto=format%2Ccompress&q=75&sharp=10&fp-x=0.5&fp-y=0.5&s=a8677784e4a1a1432f9ae026f986b083"
    },
    {
      "title": "Jira Service Management Showcase \u2013 Atlassian Sydney | 13 August 2025",
      "date": "Upcoming",
      "location": "Sydney, NSW",
      "link": "https://www.eventbrite.com.au/e/jira-service-management-showcase-atlassian-sydney-13-august-2025-tickets-1512110807129?aff=ebdssbcitybrowse",
      "image": "https://img.evbuc.com/https%3A%2F%2Fcdn.evbuc.com%2Fimages%2F1078610483%2F271528743785%2F1%2Foriginal.20250722-100626?h=230&w=460&auto=format%2Ccompress&q=75&sharp=10&rect=0%2C17%2C1260%2C630&s=b57ecde0e94573dba586b8b0fc6fe9ab"
    },
    {
      "title": "Homemade Saturdays - 26th July 2025",
      "date": "Upcoming",
      "location": "Darling Park, NSW",
      "link": "https://www.eventbrite.com.au/e/homemade-saturdays-26th-july-2025-tickets-1318209894279?aff=ebdssbcitybrowse",
      "image": "https://img.evbuc.com/https%3A%2F%2Fcdn.evbuc.com%2Fimages%2F1063143943%2F1225643091603%2F1%2Foriginal.20250630-072956?w=512&auto=format%2Ccompress&q=75&sharp=10&rect=0%2C28%2C2400%2C1200&s=894ecfd3287f646cd19c573236240cc5"
    },
    {
      "title": "Homemade Saturdays: Free Entry + Complimentary Drink",
      "date": "Upcoming",
      "location": "Sydney, NSW",
      "link": "https://www.eventbrite.com.au/e/homemade-saturdays-free-entry-complimentary-drink-tickets-887309505617?aff=ebdssbcitybrowse",
      "image": "https://img.evbuc.com/https%3A%2F%2Fcdn.evbuc.com%2Fimages%2F748918359%2F2055543935043%2F1%2Foriginal.20240422-010025?w=512&auto=format%2Ccompress&q=75&sharp=10&rect=0%2C0%2C2160%2C1080&s=6de3c49714627a4ec6139403c1c4be75"
    },
    {
      "title": "Soulmate: Hottest Sydney Sunday sesh",
      "date": "Upcoming",
      "location": "Sydney, NSW",
      "link": "https://www.eventbrite.com.au/e/soulmate-hottest-sydney-sunday-sesh-tickets-1466167960839?aff=ebdssbcitybrowse",
      "image": "https://img.evbuc.com/https%3A%2F%2Fcdn.evbuc.com%2Fimages%2F1016395983%2F370592850131%2F1%2Foriginal.20250425-001057?w=512&auto=format%2Ccompress&q=75&sharp=10&rect=0%2C608%2C7008%2C3504&s=6b901f8e138202a63ccf5fd2192670a8"
    },
    {
      "title": "Venture & Capital 2025 \u2013 Private Market Investment Conference | Sydney",
      "date": "Upcoming",
      "location": "Sydney, NSW",
      "link": "https://www.eventbrite.com.au/e/venture-capital-2025-private-market-investment-conference-sydney-tickets-1280280536549?aff=ebdssbcitybrowse",
      "image": "https://img.evbuc.com/https%3A%2F%2Fcdn.evbuc.com%2Fimages%2F1078242623%2F54901145563%2F1%2Foriginal.20250721-210902?w=512&auto=format%2Ccompress&q=75&sharp=10&rect=0%2C0%2C2160%2C1080&s=6c7a36dea75002f12a62bcb77f550e78"
    },
    {
      "title": "Sydney Tattoo Convention 2025 \u2013 Australia's Premier Tattoo Expo",
      "date": "Upcoming",
      "location": "Sydney, NSW",
      "link": "https://www.eventbrite.com.au/e/sydney-tattoo-convention-2025-australias-premier-tattoo-expo-tickets-1036514722437?aff=ebdssbcitybrowse",
      "image": "https://img.evbuc.com/https%3A%2F%2Fcdn.evbuc.com%2Fimages%2F951047303%2F203978083134%2F1%2Foriginal.20250203-055351?w=512&auto=format%2Ccompress&q=75&sharp=10&rect=0%2C0%2C9000%2C4500&s=d29d56466f8e0c7ed231ea575b30f748"
    },
    {
      "title": "Tait Micallef Fundraiser",
      "date": "Upcoming",
      "location": "Sydney, NSW",
      "link": "https://www.eventbrite.com/e/tait-micallef-fundraiser-tickets-1509188476359?aff=ebdssbcitybrowse",
      "image": "https://img.evbuc.com/https%3A%2F%2Fcdn.evbuc.com%2Fimages%2F1078572233%2F1792060733563%2F1%2Foriginal.20250722-085113?w=267&auto=format%2Ccompress&q=75&sharp=10&s=8ea97a46fe800b078ddd3b3deca3a46d"
    },
    {
      "title": "MedConnect | Endometriosis: Behind the pain",
      "date": "Upcoming",
      "location": "Sydney, NSW",
      "link": "https://www.eventbrite.com.au/e/medconnect-endometriosis-behind-the-pain-tickets-1487409725529?aff=ebdssbcitybrowse",
      "image": "https://img.evbuc.com/https%3A%2F%2Fcdn.evbuc.com%2Fimages%2F1076173013%2F244774674134%2F1%2Foriginal.20250718-025247?w=512&auto=format%2Ccompress&q=75&sharp=10&rect=0%2C0%2C2160%2C1080&s=4eb55b3df445f2ba8382ead1953e59da"
    },
    {
      "title": "Complex Caesarean Section: Prenatal Evaluation and Surgical Approach",
      "date": "Upcoming",
      "location": "online",
      "link": "https://www.eventbrite.co.uk/e/complex-caesarean-section-prenatal-evaluation-and-surgical-approach-tickets-1460710838439?aff=ebdssbcitybrowse",
      "image": "https://img.evbuc.com/https%3A%2F%2Fcdn.evbuc.com%2Fimages%2F1065943573%2F22766425176%2F1%2Foriginal.20250703-125822?w=512&auto=format%2Ccompress&q=75&sharp=10&rect=0%2C0%2C2160%2C1080&s=e8a4924815b4cf47b0c725b11b62d88f"
    },
    {
      "title": "Liveable Streets: Rethinking Urban Space with the Woonerf Concept",
      "date": "Upcoming",
      "location": "online",
      "link": "https://www.eventbrite.de/e/liveable-streets-rethinking-urban-space-with-the-woonerf-concept-tickets-1476904945449?aff=ebdssbcitybrowse",
      "image": "https://img.evbuc.com/https%3A%2F%2Fcdn.evbuc.com%2Fimages%2F1069750273%2F1544367251803%2F1%2Foriginal.20250709-110334?crop=focalpoint&fit=crop&w=512&auto=format%2Ccompress&q=75&sharp=10&fp-x=0.0770201827541&fp-y=0.202657756615&s=e7e8bbb5b20a75bbb82b321b63baac59"
    },
    {
      "title": "NASA's SpaceX Crew-11 Mission Launch",
      "date": "Upcoming",
      "location": "online",
      "link": "https://www.eventbrite.com/e/nasas-spacex-crew-11-mission-launch-registration-1328124218289?aff=ebdssbcitybrowse",
      "image": "https://img.evbuc.com/https%3A%2F%2Fcdn.evbuc.com%2Fimages%2F1010304913%2F977011528923%2F1%2Foriginal.20250416-133852?crop=focalpoint&fit=crop&w=512&auto=format%2Ccompress&q=75&sharp=10&fp-x=0.0049053030303&fp-y=0.00441860465116&s=bde9c80f3f6ef5056075446806bfa406"
    },
    {
      "title": "#ProductCon AI: Online Edition",
      "date": "Upcoming",
      "location": "online",
      "link": "https://www.eventbrite.com/e/productcon-ai-online-edition-tickets-1009144246607?aff=ebdssbcitybrowse",
      "image": "https://img.evbuc.com/https%3A%2F%2Fcdn.evbuc.com%2Fimages%2F1065048143%2F235040984945%2F1%2Foriginal.20250702-123445?crop=focalpoint&fit=crop&auto=format%2Ccompress&q=75&sharp=10&fp-x=0.477272727273&fp-y=0.565055762082&s=c8d39a981f9b72f91ca928ea014f8029"
    },
    {
      "title": "Washington DC Career Fair",
      "date": "Upcoming",
      "location": "online",
      "link": "https://www.eventbrite.com/e/washington-dc-career-fair-tickets-775204777357?aff=ebdssbcitybrowse",
      "image": "https://img.evbuc.com/https%3A%2F%2Fcdn.evbuc.com%2Fimages%2F656322669%2F316131771624%2F1%2Foriginal.20231210-193525?w=300&auto=format%2Ccompress&q=75&sharp=10&s=5214ef169b7b4b7802c68100b5fcd02f"
    },
    {
      "title": "Career Fair: Exclusive Tech Hiring Event-New Tickets Available",
      "date": "Upcoming",
      "location": "online",
      "link": "https://www.eventbrite.com/e/career-fair-exclusive-tech-hiring-event-new-tickets-available-tickets-63049080497?aff=ebdssbcitybrowse",
      "image": "https://img.evbuc.com/https%3A%2F%2Fcdn.evbuc.com%2Fimages%2F682597209%2F197361445633%2F1%2Foriginal.20240125-160053?w=512&auto=format%2Ccompress&q=75&sharp=10&rect=0%2C0%2C940%2C470&s=1790a7734766e877ae40e832f440984d"
    },
    {
      "title": "Update on the Economy Webinar Series",
      "date": "Upcoming",
      "location": "online",
      "link": "https://www.eventbrite.co.uk/e/update-on-the-economy-webinar-series-tickets-634030792167?aff=ebdssbcitybrowse",
      "image": "https://img.evbuc.com/https%3A%2F%2Fcdn.evbuc.com%2Fimages%2F667412879%2F195754839567%2F1%2Foriginal.20240104-130722?w=512&auto=format%2Ccompress&q=75&sharp=10&rect=0%2C0%2C2160%2C1080&s=d90f4fbf907bf04d421471ef97b6c8aa"
    },
    {
      "title": "No Cost On-Line Coursera Certification Courses For Military and Spouse",
      "date": "Upcoming",
      "location": "online",
      "link": "https://www.eventbrite.com/e/no-cost-on-line-coursera-certification-courses-for-military-and-spouse-tickets-165655358637?aff=ebdssbcitybrowse",
      "image": "https://img.evbuc.com/https%3A%2F%2Fcdn.evbuc.com%2Fimages%2F631748609%2F122310519079%2F1%2Foriginal.20231031-040429?w=512&auto=format%2Ccompress&q=75&sharp=10&rect=0%2C0%2C2160%2C1080&s=9b7a42e3580929f655116c091d698c90"
    },
    {
      "title": "Taking Meaningful Images in Travel Photography",
      "date": "Upcoming",
      "location": "Sydney, NSW",
      "link": "https://www.eventbrite.com.au/e/taking-meaningful-images-in-travel-photography-tickets-1445384567149?aff=ebdssbcitybrowse",
      "image": "https://img.evbuc.com/https%3A%2F%2Fcdn.evbuc.com%2Fimages%2F1063041903%2F1755117891283%2F1%2Foriginal.20250630-014526?crop=focalpoint&fit=crop&w=512&auto=format%2Ccompress&q=75&sharp=10&fp-x=0.5&fp-y=0.5&s=5a7787be63d0b62cfb2351935d08ade9"
    },
    {
      "title": "T2 QVB Breakfast Club",
      "date": "Upcoming",
      "location": "Sydney, NSW",
      "link": "https://www.eventbrite.com.au/e/t2-qvb-breakfast-club-tickets-1489670136479?aff=ebdssbcitybrowse",
      "image": "https://img.evbuc.com/https%3A%2F%2Fcdn.evbuc.com%2Fimages%2F1077594003%2F1844447773723%2F1%2Foriginal.20250721-035948?w=512&auto=format%2Ccompress&q=75&sharp=10&rect=0%2C0%2C2160%2C1080&s=dbe9200cbe6d02755a88ce35cf0cd4e8"
    },
    {
      "title": "Plaza Basement x Motive Records Takeover",
      "date": "Upcoming",
      "location": "Sydney, NSW",
      "link": "https://www.eventbrite.com/e/plaza-basement-x-motive-records-takeover-tickets-1365257876059?aff=ebdssbcitybrowse",
      "image": "https://img.evbuc.com/https%3A%2F%2Fcdn.evbuc.com%2Fimages%2F1035469703%2F2530488701891%2F1%2Foriginal.20250520-235255?crop=focalpoint&fit=crop&w=512&auto=format%2Ccompress&q=75&sharp=10&fp-x=0.948863636364&fp-y=0.498220640569&s=0fe49ed7f28cd143d77ebe268852f843"
    },
    {
      "title": "Altered States Experience | DEE WHY | Morning Session",
      "date": "Upcoming",
      "location": "Dee Why, NSW",
      "link": "https://www.eventbrite.com.au/e/altered-states-experience-dee-why-morning-session-tickets-1435965113309?aff=ebdssbcitybrowse",
      "image": "https://img.evbuc.com/https%3A%2F%2Fcdn.evbuc.com%2Fimages%2F1060912583%2F1346524549793%2F1%2Foriginal.20250626-045209?crop=focalpoint&fit=crop&w=512&auto=format%2Ccompress&q=75&sharp=10&fp-x=5e-21&fp-y=5e-21&s=5ec35ce421ce2cfb4933cecc8cbce030"
    },
    {
      "title": "The ULTIMATE Christmas In July Pub Crawl | Saturday 26 July | Sydney",
      "date": "Upcoming",
      "location": "Sydney, NSW",
      "link": "https://www.eventbrite.com/e/the-ultimate-christmas-in-july-pub-crawl-saturday-26-july-sydney-tickets-1361314461199?aff=ebdssbcitybrowse",
      "image": "https://img.evbuc.com/https%3A%2F%2Fcdn.evbuc.com%2Fimages%2F1027697513%2F154153969751%2F1%2Foriginal.20250510-035339?crop=focalpoint&fit=crop&w=512&auto=format%2Ccompress&q=75&sharp=10&fp-x=0.5&fp-y=0.5&s=8889beebe56900bb3314d401fa13e6ac"
    },
    {
      "title": "Dubai Property Expo - Sydney",
      "date": "Upcoming",
      "location": "Sydney, NSW",
      "link": "https://www.eventbrite.com/e/dubai-property-expo-sydney-tickets-1442430932749?aff=ebdssbcitybrowse",
      "image": "https://img.evbuc.com/https%3A%2F%2Fcdn.evbuc.com%2Fimages%2F1062156193%2F2301107732643%2F1%2Foriginal.20250627-185052?crop=focalpoint&fit=crop&w=512&auto=format%2Ccompress&q=75&sharp=10&fp-x=0.344357976654&fp-y=0.503089281372&s=726be2868aa0e2c13bacf26b8f1ea478"
    },
    {
      "title": "Ultimate Saturdays: Free Entry @ LVL4 Zeta Bar (Hilton Rooftop)",
      "date": "Upcoming",
      "location": "Sydney, NSW",
      "link": "https://www.eventbrite.com.au/e/ultimate-saturdays-free-entry-lvl4-zeta-bar-hilton-rooftop-tickets-1391243419519?aff=ebdssbcitybrowse",
      "image": "https://img.evbuc.com/https%3A%2F%2Fcdn.evbuc.com%2Fimages%2F1043163683%2F363582059739%2F1%2Foriginal.20250531-022007?w=512&auto=format%2Ccompress&q=75&sharp=10&rect=0%2C0%2C2160%2C1080&s=56a9cde562654e731772d6504baccc36"
    },
    {
      "title": "Family Sunday: Escape from the cold",
      "date": "Upcoming",
      "location": "Sydney, NSW",
      "link": "https://www.eventbrite.com.au/e/family-sunday-escape-from-the-cold-tickets-1422722123169?aff=ebdssbcitybrowse",
      "image": "https://img.evbuc.com/https%3A%2F%2Fcdn.evbuc.com%2Fimages%2F1056931643%2F94967186259%2F1%2Foriginal.20250619-222338?w=512&auto=format%2Ccompress&q=75&sharp=10&rect=0%2C0%2C2160%2C1080&s=1f65e072c4358d7480da41d89c8daa84"
    }
  ]
}